{
"meta":{"test_sets":[],"test_metrics":[],"learn_metrics":[{"best_value":"Min","name":"MultiClass"}],"launch_mode":"Train","parameters":"","iteration_count":1000,"learn_sets":["learn"],"name":"experiment"},
"iterations":[
{"learn":[0.6380543341],"iteration":0,"passed_time":0.1822469902,"remaining_time":182.0647432},
{"learn":[0.4864475664],"iteration":1,"passed_time":0.3269384056,"remaining_time":163.1422644},
{"learn":[0.3935467645],"iteration":2,"passed_time":0.467606527,"remaining_time":155.4012358},
{"learn":[0.348513333],"iteration":3,"passed_time":0.6036788676,"remaining_time":150.316038},
{"learn":[0.3031606727],"iteration":4,"passed_time":0.7435691003,"remaining_time":147.970251},
{"learn":[0.2781340259],"iteration":5,"passed_time":0.8806188087,"remaining_time":145.8891826},
{"learn":[0.2658613222],"iteration":6,"passed_time":1.079917803,"remaining_time":153.1940541},
{"learn":[0.2460359688],"iteration":7,"passed_time":1.218165629,"remaining_time":151.052538},
{"learn":[0.2320602293],"iteration":8,"passed_time":1.362349319,"remaining_time":150.0097972},
{"learn":[0.2227607074],"iteration":9,"passed_time":1.50079881,"remaining_time":148.5790822},
{"learn":[0.2148816792],"iteration":10,"passed_time":1.641400392,"remaining_time":147.5768171},
{"learn":[0.2097032548],"iteration":11,"passed_time":1.781009637,"remaining_time":146.6364601},
{"learn":[0.2028376534],"iteration":12,"passed_time":1.920165284,"remaining_time":145.7848565},
{"learn":[0.1962684499],"iteration":13,"passed_time":2.11110183,"remaining_time":148.681886},
{"learn":[0.1871641264],"iteration":14,"passed_time":2.251068595,"remaining_time":147.8201711},
{"learn":[0.1786071013],"iteration":15,"passed_time":2.391596033,"remaining_time":147.083156},
{"learn":[0.1737933143],"iteration":16,"passed_time":2.574203362,"remaining_time":148.8495238},
{"learn":[0.1684214029],"iteration":17,"passed_time":2.776993115,"remaining_time":151.5004022},
{"learn":[0.1642694879],"iteration":18,"passed_time":2.957213486,"remaining_time":152.6856016},
{"learn":[0.1599875843],"iteration":19,"passed_time":3.134907469,"remaining_time":153.610466},
{"learn":[0.1550945035],"iteration":20,"passed_time":3.322101954,"remaining_time":154.8732292},
{"learn":[0.1485952509],"iteration":21,"passed_time":3.458291059,"remaining_time":153.7367571},
{"learn":[0.1462659019],"iteration":22,"passed_time":3.598748342,"remaining_time":152.8685709},
{"learn":[0.1420946419],"iteration":23,"passed_time":3.790926809,"remaining_time":154.1643569},
{"learn":[0.1398006486],"iteration":24,"passed_time":3.930650938,"remaining_time":153.2953866},
{"learn":[0.1376713279],"iteration":25,"passed_time":4.095601204,"remaining_time":153.427522},
{"learn":[0.134748283],"iteration":26,"passed_time":4.237206484,"remaining_time":152.696367},
{"learn":[0.1332173865],"iteration":27,"passed_time":4.380531435,"remaining_time":152.0670198},
{"learn":[0.1310392471],"iteration":28,"passed_time":4.517809584,"remaining_time":151.2687278},
{"learn":[0.1292552695],"iteration":29,"passed_time":4.661557341,"remaining_time":150.7236874},
{"learn":[0.1270585965],"iteration":30,"passed_time":4.806714988,"remaining_time":150.2486072},
{"learn":[0.1232765545],"iteration":31,"passed_time":4.947218879,"remaining_time":149.6533711},
{"learn":[0.1204461776],"iteration":32,"passed_time":5.129160654,"remaining_time":150.2999501},
{"learn":[0.1187718676],"iteration":33,"passed_time":5.266035463,"remaining_time":149.6173605},
{"learn":[0.1151170506],"iteration":34,"passed_time":5.458435429,"remaining_time":150.4968626},
{"learn":[0.112009494],"iteration":35,"passed_time":5.648928791,"remaining_time":151.2657598},
{"learn":[0.1103522597],"iteration":36,"passed_time":5.805553197,"remaining_time":151.10129},
{"learn":[0.107677504],"iteration":37,"passed_time":5.980883617,"remaining_time":151.4107905},
{"learn":[0.106170085],"iteration":38,"passed_time":6.130207724,"remaining_time":151.0546057},
{"learn":[0.1040173501],"iteration":39,"passed_time":6.292402581,"remaining_time":151.017662},
{"learn":[0.1026784954],"iteration":40,"passed_time":6.446803712,"remaining_time":150.7923112},
{"learn":[0.09992914899],"iteration":41,"passed_time":6.629376538,"remaining_time":151.212922},
{"learn":[0.09709926013],"iteration":42,"passed_time":6.824721301,"remaining_time":151.8897276},
{"learn":[0.09499493813],"iteration":43,"passed_time":7.000497605,"remaining_time":152.1017207},
{"learn":[0.09368643185],"iteration":44,"passed_time":7.163380409,"remaining_time":152.0228509},
{"learn":[0.09185708378],"iteration":45,"passed_time":7.344014717,"remaining_time":152.3084791},
{"learn":[0.09102728138],"iteration":46,"passed_time":7.499598523,"remaining_time":152.0663275},
{"learn":[0.08962762208],"iteration":47,"passed_time":7.669363121,"remaining_time":152.1090352},
{"learn":[0.08790854375],"iteration":48,"passed_time":7.80869999,"remaining_time":151.5525243},
{"learn":[0.08698049562],"iteration":49,"passed_time":7.961473663,"remaining_time":151.2679996},
{"learn":[0.08503707477],"iteration":50,"passed_time":8.145848285,"remaining_time":151.5766671},
{"learn":[0.08302119293],"iteration":51,"passed_time":8.333117717,"remaining_time":151.9191461},
{"learn":[0.08130651981],"iteration":52,"passed_time":8.524731678,"remaining_time":152.3192622},
{"learn":[0.07994004222],"iteration":53,"passed_time":8.691499035,"remaining_time":152.2621868},
{"learn":[0.07895656449],"iteration":54,"passed_time":8.840225554,"remaining_time":151.8911482},
{"learn":[0.07827100582],"iteration":55,"passed_time":8.98106064,"remaining_time":151.3950222},
{"learn":[0.07667067805],"iteration":56,"passed_time":9.171254534,"remaining_time":151.7279478},
{"learn":[0.07498256297],"iteration":57,"passed_time":9.358737857,"remaining_time":151.9988114},
{"learn":[0.07430771626],"iteration":58,"passed_time":9.506546855,"remaining_time":151.6213659},
{"learn":[0.07310796483],"iteration":59,"passed_time":9.68006168,"remaining_time":151.6542997},
{"learn":[0.07147490538],"iteration":60,"passed_time":9.881482976,"remaining_time":152.1100412},
{"learn":[0.0701948143],"iteration":61,"passed_time":10.02020011,"remaining_time":151.5959308},
{"learn":[0.06861800212],"iteration":62,"passed_time":10.20701976,"remaining_time":151.8091669},
{"learn":[0.06737282313],"iteration":63,"passed_time":10.38142487,"remaining_time":151.8283387},
{"learn":[0.0669107513],"iteration":64,"passed_time":10.52132278,"remaining_time":151.3451816},
{"learn":[0.06646948855],"iteration":65,"passed_time":10.66561733,"remaining_time":150.9346452},
{"learn":[0.0656903239],"iteration":66,"passed_time":10.80762685,"remaining_time":150.5002366},
{"learn":[0.06444297083],"iteration":67,"passed_time":10.99143276,"remaining_time":150.6472843},
{"learn":[0.06359359534],"iteration":68,"passed_time":11.15974923,"remaining_time":150.5757468},
{"learn":[0.0624763006],"iteration":69,"passed_time":11.33980387,"remaining_time":150.6573943},
{"learn":[0.06186481287],"iteration":70,"passed_time":11.49369773,"remaining_time":150.3893689},
{"learn":[0.06075925056],"iteration":71,"passed_time":11.67218911,"remaining_time":150.4415485},
{"learn":[0.05969171252],"iteration":72,"passed_time":11.85666659,"remaining_time":150.5634236},
{"learn":[0.0588363282],"iteration":73,"passed_time":12.03176468,"remaining_time":150.55965},
{"learn":[0.05789854424],"iteration":74,"passed_time":12.17307794,"remaining_time":150.1346279},
{"learn":[0.0567150192],"iteration":75,"passed_time":12.36638236,"remaining_time":150.349175},
{"learn":[0.05615343396],"iteration":76,"passed_time":12.52048604,"remaining_time":150.0832287},
{"learn":[0.05551023505],"iteration":77,"passed_time":12.68523303,"remaining_time":149.9459597},
{"learn":[0.05473223033],"iteration":78,"passed_time":12.86440164,"remaining_time":149.9761255},
{"learn":[0.05403029315],"iteration":79,"passed_time":13.03610289,"remaining_time":149.9151832},
{"learn":[0.05355968979],"iteration":80,"passed_time":13.19291306,"remaining_time":149.6825568},
{"learn":[0.05301728149],"iteration":81,"passed_time":13.33232312,"remaining_time":149.2569833},
{"learn":[0.05214475487],"iteration":82,"passed_time":13.46984565,"remaining_time":148.8174513},
{"learn":[0.05114679065],"iteration":83,"passed_time":13.67277075,"remaining_time":149.0983096},
{"learn":[0.05057298491],"iteration":84,"passed_time":13.83159322,"remaining_time":148.8930329},
{"learn":[0.04992317818],"iteration":85,"passed_time":13.99757299,"remaining_time":148.7649036},
{"learn":[0.0492606312],"iteration":86,"passed_time":14.16883863,"remaining_time":148.6913755},
{"learn":[0.04867897214],"iteration":87,"passed_time":14.32955345,"remaining_time":148.5062812},
{"learn":[0.04827676049],"iteration":88,"passed_time":14.48384359,"remaining_time":148.2559721},
{"learn":[0.04781910021],"iteration":89,"passed_time":14.63133863,"remaining_time":147.9390906},
{"learn":[0.04701944023],"iteration":90,"passed_time":14.83899469,"remaining_time":148.2268811},
{"learn":[0.04632995491],"iteration":91,"passed_time":15.02095767,"remaining_time":148.2503213},
{"learn":[0.04536611998],"iteration":92,"passed_time":15.22076214,"remaining_time":148.4433469},
{"learn":[0.04480847408],"iteration":93,"passed_time":15.40365367,"remaining_time":148.4650024},
{"learn":[0.04405649497],"iteration":94,"passed_time":15.58530984,"remaining_time":148.4705832},
{"learn":[0.04355627845],"iteration":95,"passed_time":15.75106298,"remaining_time":148.3225097},
{"learn":[0.04318549908],"iteration":96,"passed_time":15.9027668,"remaining_time":148.0432827},
{"learn":[0.04275111037],"iteration":97,"passed_time":16.06925589,"remaining_time":147.902743},
{"learn":[0.04226602686],"iteration":98,"passed_time":16.20674469,"remaining_time":147.4977471},
{"learn":[0.04173521788],"iteration":99,"passed_time":16.37970734,"remaining_time":147.4173661},
{"learn":[0.04145294524],"iteration":100,"passed_time":16.52575746,"remaining_time":147.0956036},
{"learn":[0.04057659655],"iteration":101,"passed_time":16.66533062,"remaining_time":146.7202637},
{"learn":[0.04006527826],"iteration":102,"passed_time":16.84378333,"remaining_time":146.6880936},
{"learn":[0.039549222],"iteration":103,"passed_time":17.02130181,"remaining_time":146.6450618},
{"learn":[0.03926511121],"iteration":104,"passed_time":17.16741741,"remaining_time":146.331796},
{"learn":[0.03879746156],"iteration":105,"passed_time":17.33623667,"remaining_time":146.2131659},
{"learn":[0.03839233105],"iteration":106,"passed_time":17.51193773,"remaining_time":146.1510317},
{"learn":[0.03775677312],"iteration":107,"passed_time":17.70073599,"remaining_time":146.1949676},
{"learn":[0.03747964729],"iteration":108,"passed_time":17.85817164,"remaining_time":145.9782654},
{"learn":[0.03702410088],"iteration":109,"passed_time":17.99589085,"remaining_time":145.6031168},
{"learn":[0.03650474863],"iteration":110,"passed_time":18.17488149,"remaining_time":145.5627896},
{"learn":[0.03624312343],"iteration":111,"passed_time":18.33646391,"remaining_time":145.3819639},
{"learn":[0.03583579349],"iteration":112,"passed_time":18.47698338,"remaining_time":145.0361438},
{"learn":[0.03519238541],"iteration":113,"passed_time":18.68594368,"remaining_time":145.225843},
{"learn":[0.03485654666],"iteration":114,"passed_time":18.85724321,"remaining_time":145.1187847},
{"learn":[0.03446490435],"iteration":115,"passed_time":18.9990514,"remaining_time":144.7858745},
{"learn":[0.03423530092],"iteration":116,"passed_time":19.14642809,"remaining_time":144.4982564},
{"learn":[0.0338067087],"iteration":117,"passed_time":19.34135844,"remaining_time":144.5684588},
{"learn":[0.03342940075],"iteration":118,"passed_time":19.51265212,"remaining_time":144.4592144},
{"learn":[0.03294620926],"iteration":119,"passed_time":19.69593806,"remaining_time":144.4368791},
{"learn":[0.03270695874],"iteration":120,"passed_time":19.85625694,"remaining_time":144.2450401},
{"learn":[0.03230963401],"iteration":121,"passed_time":20.03511833,"remaining_time":144.187163},
{"learn":[0.03193391067],"iteration":122,"passed_time":20.21277921,"remaining_time":144.1187591},
{"learn":[0.03174380203],"iteration":123,"passed_time":20.3545589,"remaining_time":143.7951096},
{"learn":[0.03157595396],"iteration":124,"passed_time":20.50698682,"remaining_time":143.5489077},
{"learn":[0.03137171378],"iteration":125,"passed_time":20.65800117,"remaining_time":143.294389},
{"learn":[0.03104576299],"iteration":126,"passed_time":20.82506793,"remaining_time":143.1518449},
{"learn":[0.03063799886],"iteration":127,"passed_time":20.96844552,"remaining_time":142.8475351},
{"learn":[0.03032290898],"iteration":128,"passed_time":21.16270939,"remaining_time":142.8893014},
{"learn":[0.03015176809],"iteration":129,"passed_time":21.30508224,"remaining_time":142.5801658},
{"learn":[0.02984543476],"iteration":130,"passed_time":21.48269376,"remaining_time":142.5073349},
{"learn":[0.02951457168],"iteration":131,"passed_time":21.65010946,"remaining_time":142.3658713},
{"learn":[0.02918134754],"iteration":132,"passed_time":21.78913285,"remaining_time":142.0389337},
{"learn":[0.02885754547],"iteration":133,"passed_time":21.96808578,"remaining_time":141.9728529},
{"learn":[0.02871855947],"iteration":134,"passed_time":22.10947337,"remaining_time":141.6644034},
{"learn":[0.02841212471],"iteration":135,"passed_time":22.29027699,"remaining_time":141.6088185},
{"learn":[0.02796192794],"iteration":136,"passed_time":22.48262531,"remaining_time":141.6241288},
{"learn":[0.0277302772],"iteration":137,"passed_time":22.64453454,"remaining_time":141.4462954},
{"learn":[0.02754734366],"iteration":138,"passed_time":22.79402354,"remaining_time":141.1917573},
{"learn":[0.0271889084],"iteration":139,"passed_time":22.97410621,"remaining_time":141.1266524},
{"learn":[0.02672636436],"iteration":140,"passed_time":23.19278017,"remaining_time":141.2950225},
{"learn":[0.02653702425],"iteration":141,"passed_time":23.34804611,"remaining_time":141.0748138},
{"learn":[0.02634952545],"iteration":142,"passed_time":23.50952834,"remaining_time":140.8927677},
{"learn":[0.0261700733],"iteration":143,"passed_time":23.67568689,"remaining_time":140.7388054},
{"learn":[0.02595334482],"iteration":144,"passed_time":23.8465371,"remaining_time":140.6123395},
{"learn":[0.0258439593],"iteration":145,"passed_time":23.99588521,"remaining_time":140.359493},
{"learn":[0.02560521743],"iteration":146,"passed_time":24.14391861,"remaining_time":140.1004257},
{"learn":[0.02548961549],"iteration":147,"passed_time":24.30416712,"remaining_time":139.9131783},
{"learn":[0.02518152165],"iteration":148,"passed_time":24.5069814,"remaining_time":139.9694038},
{"learn":[0.02497891203],"iteration":149,"passed_time":24.67236923,"remaining_time":139.8100923},
{"learn":[0.02478760701],"iteration":150,"passed_time":24.84203831,"remaining_time":139.6747717},
{"learn":[0.02457073749],"iteration":151,"passed_time":25.01474351,"remaining_time":139.5559375},
{"learn":[0.02432577921],"iteration":152,"passed_time":25.19104777,"remaining_time":139.4563233},
{"learn":[0.02414855185],"iteration":153,"passed_time":25.32879879,"remaining_time":139.1439206},
{"learn":[0.02403970668],"iteration":154,"passed_time":25.48675014,"remaining_time":138.9438959},
{"learn":[0.0239220796],"iteration":155,"passed_time":25.65079892,"remaining_time":138.7773993},
{"learn":[0.02362322403],"iteration":156,"passed_time":25.85884325,"remaining_time":138.8471647},
{"learn":[0.02348555325],"iteration":157,"passed_time":26.01496202,"remaining_time":138.6366963},
{"learn":[0.02329899254],"iteration":158,"passed_time":26.18143262,"remaining_time":138.4816656},
{"learn":[0.02308616378],"iteration":159,"passed_time":26.35301598,"remaining_time":138.3533339},
{"learn":[0.02274785146],"iteration":160,"passed_time":26.54912945,"remaining_time":138.3522957},
{"learn":[0.02253876554],"iteration":161,"passed_time":26.73114688,"remaining_time":138.2759326},
{"learn":[0.02229514467],"iteration":162,"passed_time":26.9178211,"remaining_time":138.2221857},
{"learn":[0.02193422474],"iteration":163,"passed_time":27.0621374,"remaining_time":137.9508955},
{"learn":[0.02173791711],"iteration":164,"passed_time":27.24299464,"remaining_time":137.8660638},
{"learn":[0.02163065021],"iteration":165,"passed_time":27.38696792,"remaining_time":137.5947665},
{"learn":[0.02141019314],"iteration":166,"passed_time":27.5764965,"remaining_time":137.5522251},
{"learn":[0.02133297992],"iteration":167,"passed_time":27.71705577,"remaining_time":137.2654191},
{"learn":[0.02121055624],"iteration":168,"passed_time":27.88624778,"remaining_time":137.1211355},
{"learn":[0.02097777885],"iteration":169,"passed_time":28.07061456,"remaining_time":137.0506476},
{"learn":[0.02083196793],"iteration":170,"passed_time":28.23964435,"remaining_time":136.9044747},
{"learn":[0.02060019676],"iteration":171,"passed_time":28.42664756,"remaining_time":136.8445592},
{"learn":[0.02040013519],"iteration":172,"passed_time":28.62045336,"remaining_time":136.8156932},
{"learn":[0.0202788445],"iteration":173,"passed_time":28.77534836,"remaining_time":136.6002169},
{"learn":[0.02006469101],"iteration":174,"passed_time":28.95613503,"remaining_time":136.5074937},
{"learn":[0.01991993702],"iteration":175,"passed_time":29.09318285,"remaining_time":136.2089924},
{"learn":[0.01978507417],"iteration":176,"passed_time":29.25641227,"remaining_time":136.0340525},
{"learn":[0.01969812512],"iteration":177,"passed_time":29.412116,"remaining_time":135.8244908},
{"learn":[0.0195460851],"iteration":178,"passed_time":29.57955288,"remaining_time":135.6693459},
{"learn":[0.01940280956],"iteration":179,"passed_time":29.74861869,"remaining_time":135.5214851},
{"learn":[0.01929363321],"iteration":180,"passed_time":29.89013351,"remaining_time":135.2487257},
{"learn":[0.01912999386],"iteration":181,"passed_time":30.07907348,"remaining_time":135.190561},
{"learn":[0.01893678255],"iteration":182,"passed_time":30.21784787,"remaining_time":134.9070039},
{"learn":[0.01882883427],"iteration":183,"passed_time":30.37876172,"remaining_time":134.7232041},
{"learn":[0.01856489713],"iteration":184,"passed_time":30.51436923,"remaining_time":134.4281672},
{"learn":[0.01846419526],"iteration":185,"passed_time":30.66940048,"remaining_time":134.2198494},
{"learn":[0.01830304851],"iteration":186,"passed_time":30.81146511,"remaining_time":133.955728},
{"learn":[0.0181964408],"iteration":187,"passed_time":30.98133005,"remaining_time":133.8129787},
{"learn":[0.01806763432],"iteration":188,"passed_time":31.16181058,"remaining_time":133.7154941},
{"learn":[0.01794268636],"iteration":189,"passed_time":31.33195398,"remaining_time":133.573067},
{"learn":[0.01780740517],"iteration":190,"passed_time":31.49623079,"remaining_time":133.4055011},
{"learn":[0.01750321897],"iteration":191,"passed_time":31.63454629,"remaining_time":133.1287156},
{"learn":[0.0173205564],"iteration":192,"passed_time":31.84763411,"remaining_time":133.1660141},
{"learn":[0.01719099089],"iteration":193,"passed_time":31.99042637,"remaining_time":132.9086786},
{"learn":[0.01704676934],"iteration":194,"passed_time":32.18151506,"remaining_time":132.8518955},
{"learn":[0.01692375143],"iteration":195,"passed_time":32.36715885,"remaining_time":132.7714067},
{"learn":[0.01679993013],"iteration":196,"passed_time":32.54193849,"remaining_time":132.6455665},
{"learn":[0.01669552661],"iteration":197,"passed_time":32.70811492,"remaining_time":132.4843847},
{"learn":[0.0166016655],"iteration":198,"passed_time":32.87154636,"remaining_time":132.3121037},
{"learn":[0.01654269113],"iteration":199,"passed_time":33.01170605,"remaining_time":132.0468242},
{"learn":[0.01645218463],"iteration":200,"passed_time":33.17340482,"remaining_time":131.8684102},
{"learn":[0.01630342317],"iteration":201,"passed_time":33.36122874,"remaining_time":131.793369},
{"learn":[0.01615322131],"iteration":202,"passed_time":33.56364714,"remaining_time":131.7745161},
{"learn":[0.01609510896],"iteration":203,"passed_time":33.7081082,"remaining_time":131.5277163},
{"learn":[0.01603129044],"iteration":204,"passed_time":33.85634763,"remaining_time":131.2965676},
{"learn":[0.01592547979],"iteration":205,"passed_time":34.03477782,"remaining_time":131.1825902},
{"learn":[0.01580938346],"iteration":206,"passed_time":34.20372515,"remaining_time":131.031662},
{"learn":[0.01571691204],"iteration":207,"passed_time":34.38552527,"remaining_time":130.9295001},
{"learn":[0.01565180999],"iteration":208,"passed_time":34.55328874,"remaining_time":130.7734516},
{"learn":[0.01554953144],"iteration":209,"passed_time":34.72807128,"remaining_time":130.6436967},
{"learn":[0.01544129159],"iteration":210,"passed_time":34.90939808,"remaining_time":130.5379862},
{"learn":[0.01539171394],"iteration":211,"passed_time":35.05894902,"remaining_time":130.313452},
{"learn":[0.01526787838],"iteration":212,"passed_time":35.24100431,"remaining_time":130.2097201},
{"learn":[0.01517750816],"iteration":213,"passed_time":35.42085964,"remaining_time":130.0971761},
{"learn":[0.01510366223],"iteration":214,"passed_time":35.59297157,"remaining_time":129.9557334},
{"learn":[0.01498567863],"iteration":215,"passed_time":35.73479081,"remaining_time":129.7040555},
{"learn":[0.01486584103],"iteration":216,"passed_time":35.93019831,"remaining_time":129.6467524},
{"learn":[0.0147566932],"iteration":217,"passed_time":36.10757927,"remaining_time":129.5235183},
{"learn":[0.01466898987],"iteration":218,"passed_time":36.27245658,"remaining_time":129.355199},
{"learn":[0.01454807949],"iteration":219,"passed_time":36.45991757,"remaining_time":129.2669805},
{"learn":[0.01450696366],"iteration":220,"passed_time":36.60208982,"remaining_time":129.0182261},
{"learn":[0.01438094133],"iteration":221,"passed_time":36.8018847,"remaining_time":128.9723707},
{"learn":[0.01427514495],"iteration":222,"passed_time":36.98517099,"remaining_time":128.8676137},
{"learn":[0.01422782537],"iteration":223,"passed_time":37.13669744,"remaining_time":128.6521304},
{"learn":[0.01409745012],"iteration":224,"passed_time":37.34068028,"remaining_time":128.6178987},
{"learn":[0.01403743942],"iteration":225,"passed_time":37.50822799,"remaining_time":128.4573826},
{"learn":[0.01396125144],"iteration":226,"passed_time":37.6836837,"remaining_time":128.3237335},
{"learn":[0.01378296873],"iteration":227,"passed_time":37.8229146,"remaining_time":128.0670617},
{"learn":[0.01367519792],"iteration":228,"passed_time":38.00857415,"remaining_time":127.9677322},
{"learn":[0.01359232449],"iteration":229,"passed_time":38.19031882,"remaining_time":127.8545456},
{"learn":[0.01351883827],"iteration":230,"passed_time":38.35765587,"remaining_time":127.6928024},
{"learn":[0.01325646593],"iteration":231,"passed_time":38.49569175,"remaining_time":127.4340141},
{"learn":[0.01318126121],"iteration":232,"passed_time":38.67499732,"remaining_time":127.3121156},
{"learn":[0.01311968174],"iteration":233,"passed_time":38.83806761,"remaining_time":127.1365803},
{"learn":[0.01308786042],"iteration":234,"passed_time":38.98239454,"remaining_time":126.9001354},
{"learn":[0.01300809044],"iteration":235,"passed_time":39.15211938,"remaining_time":126.7466915},
{"learn":[0.01291562299],"iteration":236,"passed_time":39.32591579,"remaining_time":126.6062183},
{"learn":[0.01283802392],"iteration":237,"passed_time":39.46488217,"remaining_time":126.3539505},
{"learn":[0.01276244206],"iteration":238,"passed_time":39.63885403,"remaining_time":126.2140917},
{"learn":[0.01269004605],"iteration":239,"passed_time":39.8092504,"remaining_time":126.0626263},
{"learn":[0.01259878925],"iteration":240,"passed_time":39.99815108,"remaining_time":125.9692808},
{"learn":[0.0125341808],"iteration":241,"passed_time":40.16744054,"remaining_time":125.8137187},
{"learn":[0.01249218709],"iteration":242,"passed_time":40.32527919,"remaining_time":125.6223718},
{"learn":[0.01242028231],"iteration":243,"passed_time":40.4639127,"remaining_time":125.3717951},
{"learn":[0.0123392898],"iteration":244,"passed_time":40.64519365,"remaining_time":125.2535559},
{"learn":[0.01225581976],"iteration":245,"passed_time":40.83409402,"remaining_time":125.1581581},
{"learn":[0.01218545522],"iteration":246,"passed_time":41.01339811,"remaining_time":125.0327481},
{"learn":[0.01211473018],"iteration":247,"passed_time":41.19057224,"remaining_time":124.9004449},
{"learn":[0.01207440586],"iteration":248,"passed_time":41.34242189,"remaining_time":124.691401},
{"learn":[0.01199972326],"iteration":249,"passed_time":41.53803023,"remaining_time":124.6140907},
{"learn":[0.0119203122],"iteration":250,"passed_time":41.73661321,"remaining_time":124.5447143},
{"learn":[0.01187839217],"iteration":251,"passed_time":41.89353821,"remaining_time":124.350661},
{"learn":[0.011828107],"iteration":252,"passed_time":42.05525969,"remaining_time":124.1710632},
{"learn":[0.01175539566],"iteration":253,"passed_time":42.2330834,"remaining_time":124.0388985},
{"learn":[0.01170270901],"iteration":254,"passed_time":42.38397743,"remaining_time":123.8276988},
{"learn":[0.01166099974],"iteration":255,"passed_time":42.54530601,"remaining_time":123.6472956},
{"learn":[0.01161552544],"iteration":256,"passed_time":42.72065374,"remaining_time":123.5075709},
{"learn":[0.01156664343],"iteration":257,"passed_time":42.88861892,"remaining_time":123.3463381},
{"learn":[0.01149976741],"iteration":258,"passed_time":43.03343275,"remaining_time":123.1188173},
{"learn":[0.01145006775],"iteration":259,"passed_time":43.19192811,"remaining_time":122.9308723},
{"learn":[0.01138120225],"iteration":260,"passed_time":43.37250512,"remaining_time":122.8056754},
{"learn":[0.01129649225],"iteration":261,"passed_time":43.57851729,"remaining_time":122.7517014},
{"learn":[0.01120225321],"iteration":262,"passed_time":43.72205766,"remaining_time":122.5215076},
{"learn":[0.01113849491],"iteration":263,"passed_time":43.91414665,"remaining_time":122.4273179},
{"learn":[0.01108412699],"iteration":264,"passed_time":44.09686024,"remaining_time":122.306386},
{"learn":[0.01103600243],"iteration":265,"passed_time":44.25935059,"remaining_time":122.1291855},
{"learn":[0.01093684793],"iteration":266,"passed_time":44.40109325,"remaining_time":121.8951361},
{"learn":[0.01088137],"iteration":267,"passed_time":44.56894553,"remaining_time":121.73309},
{"learn":[0.01081497728],"iteration":268,"passed_time":44.76215978,"remaining_time":121.6399212},
{"learn":[0.01074245292],"iteration":269,"passed_time":44.96183151,"remaining_time":121.5634704},
{"learn":[0.01070378451],"iteration":270,"passed_time":45.11328068,"remaining_time":121.3563897},
{"learn":[0.01066415742],"iteration":271,"passed_time":45.25564566,"remaining_time":121.1254046},
{"learn":[0.01053927126],"iteration":272,"passed_time":45.39597281,"remaining_time":120.8896419},
{"learn":[0.01050240772],"iteration":273,"passed_time":45.54412519,"remaining_time":120.6753098},
{"learn":[0.01047391963],"iteration":274,"passed_time":45.69445404,"remaining_time":120.467197},
{"learn":[0.01041894401],"iteration":275,"passed_time":45.86507985,"remaining_time":120.3127457},
{"learn":[0.0103881313],"iteration":276,"passed_time":46.01983478,"remaining_time":120.1167529},
{"learn":[0.01031993926],"iteration":277,"passed_time":46.20813223,"remaining_time":120.0081708},
{"learn":[0.01024633024],"iteration":278,"passed_time":46.42860078,"remaining_time":119.9821547},
{"learn":[0.01017431454],"iteration":279,"passed_time":46.63688851,"remaining_time":119.9234276},
{"learn":[0.01007211442],"iteration":280,"passed_time":46.77419676,"remaining_time":119.6820195},
{"learn":[0.01003294132],"iteration":281,"passed_time":46.91829235,"remaining_time":119.4586309},
{"learn":[0.00998073639],"iteration":282,"passed_time":47.09149572,"remaining_time":119.3095492},
{"learn":[0.009917649958],"iteration":283,"passed_time":47.27697248,"remaining_time":119.1912405},
{"learn":[0.009875651496],"iteration":284,"passed_time":47.41892172,"remaining_time":118.9632597},
{"learn":[0.009822502144],"iteration":285,"passed_time":47.58889122,"remaining_time":118.8058333},
{"learn":[0.009772106049],"iteration":286,"passed_time":47.77011819,"remaining_time":118.6762867},
{"learn":[0.009721453247],"iteration":287,"passed_time":47.94611666,"remaining_time":118.5334551},
{"learn":[0.009688485468],"iteration":288,"passed_time":48.11592586,"remaining_time":118.3751671},
{"learn":[0.009654393409],"iteration":289,"passed_time":48.27319207,"remaining_time":118.1860909},
{"learn":[0.009618178768],"iteration":290,"passed_time":48.43184466,"remaining_time":118.0006112},
{"learn":[0.009563241185],"iteration":291,"passed_time":48.62474879,"remaining_time":117.8983635},
{"learn":[0.009541442519],"iteration":292,"passed_time":48.78300132,"remaining_time":117.7118837},
{"learn":[0.009472726765],"iteration":293,"passed_time":48.99910664,"remaining_time":117.6645214},
{"learn":[0.009413903722],"iteration":294,"passed_time":49.21270811,"remaining_time":117.6100312},
{"learn":[0.009364466315],"iteration":295,"passed_time":49.39558832,"remaining_time":117.4813992},
{"learn":[0.009282821741],"iteration":296,"passed_time":49.53329716,"remaining_time":117.2454812},
{"learn":[0.009242396003],"iteration":297,"passed_time":49.69736277,"remaining_time":117.0723109},
{"learn":[0.00919757456],"iteration":298,"passed_time":49.8828935,"remaining_time":116.9495262},
{"learn":[0.009158023525],"iteration":299,"passed_time":50.02445028,"remaining_time":116.7237173},
{"learn":[0.00912464771],"iteration":300,"passed_time":50.18914508,"remaining_time":116.5522007},
{"learn":[0.009058312831],"iteration":301,"passed_time":50.41234593,"remaining_time":116.5159518},
{"learn":[0.009021725806],"iteration":302,"passed_time":50.58816292,"remaining_time":116.3694705},
{"learn":[0.00900161554],"iteration":303,"passed_time":50.73187375,"remaining_time":116.1492899},
{"learn":[0.008967831688],"iteration":304,"passed_time":50.89388616,"remaining_time":115.9713144},
{"learn":[0.008855524148],"iteration":305,"passed_time":51.03164909,"remaining_time":115.738446},
{"learn":[0.008813754661],"iteration":306,"passed_time":51.21495848,"remaining_time":115.6090105},
{"learn":[0.008751828955],"iteration":307,"passed_time":51.35522608,"remaining_time":115.3825209},
{"learn":[0.008706367331],"iteration":308,"passed_time":51.53320327,"remaining_time":115.2409173},
{"learn":[0.00868192633],"iteration":309,"passed_time":51.68663242,"remaining_time":115.0444399},
{"learn":[0.008640335112],"iteration":310,"passed_time":51.86959641,"remaining_time":114.9136718},
{"learn":[0.008613787374],"iteration":311,"passed_time":52.02740334,"remaining_time":114.7270945},
{"learn":[0.00858740602],"iteration":312,"passed_time":52.18343306,"remaining_time":114.5368004},
{"learn":[0.008538119151],"iteration":313,"passed_time":52.39735769,"remaining_time":114.4732082},
{"learn":[0.008508577295],"iteration":314,"passed_time":52.57115065,"remaining_time":114.3213911},
{"learn":[0.008474337868],"iteration":315,"passed_time":52.75085538,"remaining_time":114.1822313},
{"learn":[0.008453058954],"iteration":316,"passed_time":52.90030831,"remaining_time":113.9776359},
{"learn":[0.008412918444],"iteration":317,"passed_time":53.08320256,"remaining_time":113.8451074},
{"learn":[0.008390706195],"iteration":318,"passed_time":53.24210405,"remaining_time":113.6610434},
{"learn":[0.008368568423],"iteration":319,"passed_time":53.39311583,"remaining_time":113.4603711},
{"learn":[0.008319495476],"iteration":320,"passed_time":53.53466675,"remaining_time":113.239996},
{"learn":[0.008278019142],"iteration":321,"passed_time":53.72255335,"remaining_time":113.1176745},
{"learn":[0.008223398481],"iteration":322,"passed_time":53.86394733,"remaining_time":112.8974995},
{"learn":[0.008193687864],"iteration":323,"passed_time":54.02238572,"remaining_time":112.7133727},
{"learn":[0.008147681135],"iteration":324,"passed_time":54.16107549,"remaining_time":112.4883876},
{"learn":[0.008119974256],"iteration":325,"passed_time":54.32264946,"remaining_time":112.3112446},
{"learn":[0.008078566852],"iteration":326,"passed_time":54.51679714,"remaining_time":112.2012369},
{"learn":[0.008050814812],"iteration":327,"passed_time":54.68233161,"remaining_time":112.032094},
{"learn":[0.008013968704],"iteration":328,"passed_time":54.86930831,"remaining_time":111.9067048},
{"learn":[0.007979383832],"iteration":329,"passed_time":55.05119437,"remaining_time":111.7706068},
{"learn":[0.007933529225],"iteration":330,"passed_time":55.19280386,"remaining_time":111.5528271},
{"learn":[0.007906011707],"iteration":331,"passed_time":55.36472858,"remaining_time":111.3965021},
{"learn":[0.007873850493],"iteration":332,"passed_time":55.54731015,"remaining_time":111.261429},
{"learn":[0.007839072299],"iteration":333,"passed_time":55.717507,"remaining_time":111.1013762},
{"learn":[0.00781092173],"iteration":334,"passed_time":55.8751831,"remaining_time":110.9164083},
{"learn":[0.007791079263],"iteration":335,"passed_time":56.03249107,"remaining_time":110.7308752},
{"learn":[0.007750033942],"iteration":336,"passed_time":56.22366456,"remaining_time":110.6121353},
{"learn":[0.007721877035],"iteration":337,"passed_time":56.38641897,"remaining_time":110.4373058},
{"learn":[0.007695484588],"iteration":338,"passed_time":56.56045566,"remaining_time":110.2845463},
{"learn":[0.007658897564],"iteration":339,"passed_time":56.69741205,"remaining_time":110.0596822},
{"learn":[0.007631624075],"iteration":340,"passed_time":56.86963176,"remaining_time":109.9034819},
{"learn":[0.007603899766],"iteration":341,"passed_time":57.04428567,"remaining_time":109.7518713},
{"learn":[0.007576897245],"iteration":342,"passed_time":57.21518457,"remaining_time":109.5929337},
{"learn":[0.007556653872],"iteration":343,"passed_time":57.3868719,"remaining_time":109.4354301},
{"learn":[0.007532151072],"iteration":344,"passed_time":57.54913803,"remaining_time":109.2599577},
{"learn":[0.007507195073],"iteration":345,"passed_time":57.71959458,"remaining_time":109.1000429},
{"learn":[0.007491371965],"iteration":346,"passed_time":57.87116572,"remaining_time":108.904528},
{"learn":[0.00745457498],"iteration":347,"passed_time":58.05265735,"remaining_time":108.7653235},
{"learn":[0.007411865028],"iteration":348,"passed_time":58.19399114,"remaining_time":108.5509691},
{"learn":[0.007392991549],"iteration":349,"passed_time":58.35124664,"remaining_time":108.3666009},
{"learn":[0.007364355298],"iteration":350,"passed_time":58.52665388,"remaining_time":108.2159498},
{"learn":[0.007338597487],"iteration":351,"passed_time":58.70861384,"remaining_time":108.0772209},
{"learn":[0.007309741767],"iteration":352,"passed_time":58.87927153,"remaining_time":107.9175317},
{"learn":[0.007276705058],"iteration":353,"passed_time":59.06351572,"remaining_time":107.7825739},
{"learn":[0.007258435315],"iteration":354,"passed_time":59.22464215,"remaining_time":107.6053357},
{"learn":[0.007235764321],"iteration":355,"passed_time":59.39482658,"remaining_time":107.4445739},
{"learn":[0.007208861631],"iteration":356,"passed_time":59.57302168,"remaining_time":107.2981875},
{"learn":[0.007176633072],"iteration":357,"passed_time":59.77213527,"remaining_time":107.1891364},
{"learn":[0.007156303338],"iteration":358,"passed_time":59.93781225,"remaining_time":107.019882},
{"learn":[0.007124863914],"iteration":359,"passed_time":60.11928845,"remaining_time":106.878735},
{"learn":[0.007099587032],"iteration":360,"passed_time":60.28926658,"remaining_time":106.717012},
{"learn":[0.007069422425],"iteration":361,"passed_time":60.47267512,"remaining_time":106.5789136},
{"learn":[0.007042966595],"iteration":362,"passed_time":60.64699801,"remaining_time":106.4246219},
{"learn":[0.007021572796],"iteration":363,"passed_time":60.81329755,"remaining_time":106.2562012},
{"learn":[0.006993880179],"iteration":364,"passed_time":60.99453697,"remaining_time":106.1137835},
{"learn":[0.006964515799],"iteration":365,"passed_time":61.14439284,"remaining_time":105.9167898},
{"learn":[0.006949199766],"iteration":366,"passed_time":61.2912601,"remaining_time":105.7148982},
{"learn":[0.006933039929],"iteration":367,"passed_time":61.45850929,"remaining_time":105.5483094},
{"learn":[0.006904802207],"iteration":368,"passed_time":61.6394894,"remaining_time":105.4051973},
{"learn":[0.006875379197],"iteration":369,"passed_time":61.82574978,"remaining_time":105.2708712},
{"learn":[0.006855877421],"iteration":370,"passed_time":62.00092527,"remaining_time":105.1174717},
{"learn":[0.006833433026],"iteration":371,"passed_time":62.15960819,"remaining_time":104.9361128},
{"learn":[0.006810000629],"iteration":372,"passed_time":62.33920209,"remaining_time":104.790026},
{"learn":[0.006784820408],"iteration":373,"passed_time":62.52505419,"remaining_time":104.6542351},
{"learn":[0.006762383145],"iteration":374,"passed_time":62.70944751,"remaining_time":104.5157459},
{"learn":[0.006733794431],"iteration":375,"passed_time":62.90405132,"remaining_time":104.3939575},
{"learn":[0.006717357288],"iteration":376,"passed_time":63.05944416,"remaining_time":104.206986},
{"learn":[0.006701355119],"iteration":377,"passed_time":63.2191832,"remaining_time":104.0273332},
{"learn":[0.006677221532],"iteration":378,"passed_time":63.39358398,"remaining_time":103.8718091},
{"learn":[0.006663498823],"iteration":379,"passed_time":63.53629893,"remaining_time":103.6644877},
{"learn":[0.006639233318],"iteration":380,"passed_time":63.71566842,"remaining_time":103.5170571},
{"learn":[0.006621108962],"iteration":381,"passed_time":63.87020529,"remaining_time":103.329285},
{"learn":[0.006601996603],"iteration":382,"passed_time":64.01005867,"remaining_time":103.1180319},
{"learn":[0.006587197945],"iteration":383,"passed_time":64.17390853,"remaining_time":102.9456449},
{"learn":[0.006563217273],"iteration":384,"passed_time":64.34478092,"remaining_time":102.7845202},
{"learn":[0.006546553927],"iteration":385,"passed_time":64.50951878,"remaining_time":102.6135869},
{"learn":[0.006525233812],"iteration":386,"passed_time":64.64667768,"remaining_time":102.3990011},
{"learn":[0.006505463445],"iteration":387,"passed_time":64.81363096,"remaining_time":102.2318097},
{"learn":[0.006482404222],"iteration":388,"passed_time":64.98574065,"remaining_time":102.0727186},
{"learn":[0.006467495038],"iteration":389,"passed_time":65.13805751,"remaining_time":101.8826028},
{"learn":[0.006441334737],"iteration":390,"passed_time":65.28271294,"remaining_time":101.6807473},
{"learn":[0.006420001945],"iteration":391,"passed_time":65.45327896,"remaining_time":101.5193714},
{"learn":[0.006402573233],"iteration":392,"passed_time":65.62264194,"remaining_time":101.3560907},
{"learn":[0.006380551929],"iteration":393,"passed_time":65.80447204,"remaining_time":101.2119545},
{"learn":[0.006356047148],"iteration":394,"passed_time":65.94412113,"remaining_time":101.003021},
{"learn":[0.006334730599],"iteration":395,"passed_time":66.11435384,"remaining_time":100.8410851},
{"learn":[0.006304590554],"iteration":396,"passed_time":66.25251847,"remaining_time":100.6303996},
{"learn":[0.006286709436],"iteration":397,"passed_time":66.39660501,"remaining_time":100.4290357},
{"learn":[0.006273592047],"iteration":398,"passed_time":66.56064472,"remaining_time":100.2580137},
{"learn":[0.006255960505],"iteration":399,"passed_time":66.72105007,"remaining_time":100.0815751},
{"learn":[0.006238117021],"iteration":400,"passed_time":66.88910141,"remaining_time":99.91663776},
{"learn":[0.006218332392],"iteration":401,"passed_time":67.05698013,"remaining_time":99.75142816},
{"learn":[0.006154806628],"iteration":402,"passed_time":67.19794845,"remaining_time":99.54634051},
{"learn":[0.006140729758],"iteration":403,"passed_time":67.35908479,"remaining_time":99.37132311},
{"learn":[0.006126605747],"iteration":404,"passed_time":67.51902333,"remaining_time":99.19461452},
{"learn":[0.006106417043],"iteration":405,"passed_time":67.68651329,"remaining_time":99.02903669},
{"learn":[0.006093096824],"iteration":406,"passed_time":67.84500315,"remaining_time":98.85033628},
{"learn":[0.006070130698],"iteration":407,"passed_time":68.02955524,"remaining_time":98.70955074},
{"learn":[0.006050985062],"iteration":408,"passed_time":68.17773149,"remaining_time":98.51598854},
{"learn":[0.006013030917],"iteration":409,"passed_time":68.31616626,"remaining_time":98.3086295},
{"learn":[0.005989049056],"iteration":410,"passed_time":68.50575935,"remaining_time":98.17492033},
{"learn":[0.005973581693],"iteration":411,"passed_time":68.66787007,"remaining_time":98.00171748},
{"learn":[0.005950434525],"iteration":412,"passed_time":68.83735349,"remaining_time":97.83904721},
{"learn":[0.005939421496],"iteration":413,"passed_time":69.01054462,"remaining_time":97.68159214},
{"learn":[0.005916299286],"iteration":414,"passed_time":69.19699493,"remaining_time":97.54275189},
{"learn":[0.005896857328],"iteration":415,"passed_time":69.38497652,"remaining_time":97.40583242},
{"learn":[0.005881679949],"iteration":416,"passed_time":69.54916364,"remaining_time":97.23540145},
{"learn":[0.005865714622],"iteration":417,"passed_time":69.71963826,"remaining_time":97.0737547},
{"learn":[0.005845375777],"iteration":418,"passed_time":69.89786864,"remaining_time":96.92282023},
{"learn":[0.005773271338],"iteration":419,"passed_time":70.03905357,"remaining_time":96.72059779},
{"learn":[0.005750568653],"iteration":420,"passed_time":70.23123824,"remaining_time":96.58880508},
{"learn":[0.005732099645],"iteration":421,"passed_time":70.41328186,"remaining_time":96.44283629},
{"learn":[0.005717452317],"iteration":422,"passed_time":70.580809,"remaining_time":96.2768955},
{"learn":[0.005704880825],"iteration":423,"passed_time":70.73558207,"remaining_time":96.09362092},
{"learn":[0.00568498567],"iteration":424,"passed_time":70.91480103,"remaining_time":95.94355433},
{"learn":[0.005675511296],"iteration":425,"passed_time":71.05819044,"remaining_time":95.7450735},
{"learn":[0.005657685639],"iteration":426,"passed_time":71.23520102,"remaining_time":95.59196765},
{"learn":[0.005641750024],"iteration":427,"passed_time":71.37565044,"remaining_time":95.38988798},
{"learn":[0.005623322613],"iteration":428,"passed_time":71.55658855,"remaining_time":95.24198615},
{"learn":[0.005602468769],"iteration":429,"passed_time":71.74091236,"remaining_time":95.09841871},
{"learn":[0.005590349684],"iteration":430,"passed_time":71.8966229,"remaining_time":94.91688731},
{"learn":[0.005569832173],"iteration":431,"passed_time":72.10428661,"remaining_time":94.80378424},
{"learn":[0.005554580317],"iteration":432,"passed_time":72.28015522,"remaining_time":94.64860973},
{"learn":[0.00553686796],"iteration":433,"passed_time":72.42516091,"remaining_time":94.45309003},
{"learn":[0.005516926059],"iteration":434,"passed_time":72.61821493,"remaining_time":94.32021019},
{"learn":[0.005501447207],"iteration":435,"passed_time":72.77370491,"remaining_time":94.13846232},
{"learn":[0.005484415439],"iteration":436,"passed_time":72.94545331,"remaining_time":93.97778081},
{"learn":[0.005469058206],"iteration":437,"passed_time":73.11995916,"remaining_time":93.82058687},
{"learn":[0.00545439424],"iteration":438,"passed_time":73.28804861,"remaining_time":93.65511451},
{"learn":[0.005441480869],"iteration":439,"passed_time":73.45856708,"remaining_time":93.49272174},
{"learn":[0.005428458557],"iteration":440,"passed_time":73.59979725,"remaining_time":93.29316704},
{"learn":[0.005408040085],"iteration":441,"passed_time":73.80219119,"remaining_time":93.17109205},
{"learn":[0.005389481943],"iteration":442,"passed_time":73.97669127,"remaining_time":93.01358247},
{"learn":[0.005376244916],"iteration":443,"passed_time":74.14731201,"remaining_time":92.85113846},
{"learn":[0.005367154017],"iteration":444,"passed_time":74.30492868,"remaining_time":92.67243914},
{"learn":[0.005350618628],"iteration":445,"passed_time":74.49056908,"remaining_time":92.5286441},
{"learn":[0.005340358288],"iteration":446,"passed_time":74.64741991,"remaining_time":92.34904521},
{"learn":[0.005326901397],"iteration":447,"passed_time":74.81363311,"remaining_time":92.18108365},
{"learn":[0.005310504661],"iteration":448,"passed_time":74.95488405,"remaining_time":91.98249691},
{"learn":[0.005297066389],"iteration":449,"passed_time":75.10232534,"remaining_time":91.79173097},
{"learn":[0.005279924887],"iteration":450,"passed_time":75.27442075,"remaining_time":91.63116849},
{"learn":[0.005268414687],"iteration":451,"passed_time":75.45121101,"remaining_time":91.47624697},
{"learn":[0.005255055646],"iteration":452,"passed_time":75.63362836,"remaining_time":91.32802364},
{"learn":[0.005243724111],"iteration":453,"passed_time":75.78152218,"remaining_time":91.13813019},
{"learn":[0.005223590076],"iteration":454,"passed_time":75.98354977,"remaining_time":91.01326291},
{"learn":[0.005215222154],"iteration":455,"passed_time":76.13293576,"remaining_time":90.8252567},
{"learn":[0.00519953255],"iteration":456,"passed_time":76.3034489,"remaining_time":90.66252244},
{"learn":[0.005181656186],"iteration":457,"passed_time":76.44310545,"remaining_time":90.46323833},
{"learn":[0.005165205969],"iteration":458,"passed_time":76.62684974,"remaining_time":90.31617802},
{"learn":[0.005150470695],"iteration":459,"passed_time":76.80474973,"remaining_time":90.16209751},
{"learn":[0.005131454601],"iteration":460,"passed_time":77.00643978,"remaining_time":90.03572894},
{"learn":[0.005120545365],"iteration":461,"passed_time":77.1551298,"remaining_time":89.84731566},
{"learn":[0.005111290459],"iteration":462,"passed_time":77.30965726,"remaining_time":89.66584438},
{"learn":[0.00509751625],"iteration":463,"passed_time":77.48302343,"remaining_time":89.5062512},
{"learn":[0.005081354828],"iteration":464,"passed_time":77.6480367,"remaining_time":89.33698847},
{"learn":[0.005063621475],"iteration":465,"passed_time":77.84502425,"remaining_time":89.20438401},
{"learn":[0.005049791805],"iteration":466,"passed_time":77.98481568,"remaining_time":89.00622432},
{"learn":[0.005034709105],"iteration":467,"passed_time":78.15730036,"remaining_time":88.84547818},
{"learn":[0.00501643025],"iteration":468,"passed_time":78.29621716,"remaining_time":88.64667657},
{"learn":[0.005005299168],"iteration":469,"passed_time":78.46155643,"remaining_time":88.47792534},
{"learn":[0.004993096099],"iteration":470,"passed_time":78.6272338,"remaining_time":88.30956832},
{"learn":[0.004979008533],"iteration":471,"passed_time":78.76859433,"remaining_time":88.11402078},
{"learn":[0.004966643437],"iteration":472,"passed_time":78.93961056,"remaining_time":87.95174369},
{"learn":[0.004955291699],"iteration":473,"passed_time":79.11801143,"remaining_time":87.7976245},
{"learn":[0.004940061234],"iteration":474,"passed_time":79.30471391,"remaining_time":87.65257853},
{"learn":[0.004928089914],"iteration":475,"passed_time":79.47414814,"remaining_time":87.48834795},
{"learn":[0.004915476034],"iteration":476,"passed_time":79.64413358,"remaining_time":87.32469992},
{"learn":[0.004901138101],"iteration":477,"passed_time":79.8229447,"remaining_time":87.17066345},
{"learn":[0.004887046574],"iteration":478,"passed_time":80.00593905,"remaining_time":87.02107358},
{"learn":[0.00487516003],"iteration":479,"passed_time":80.19082171,"remaining_time":86.87339018},
{"learn":[0.00486555651],"iteration":480,"passed_time":80.32906821,"remaining_time":86.6752316},
{"learn":[0.004850216708],"iteration":481,"passed_time":80.50848024,"remaining_time":86.52156175},
{"learn":[0.004800247269],"iteration":482,"passed_time":80.64823417,"remaining_time":86.32533555},
{"learn":[0.004792944997],"iteration":483,"passed_time":80.80650237,"remaining_time":86.14908103},
{"learn":[0.004782593146],"iteration":484,"passed_time":80.97807526,"remaining_time":85.98702837},
{"learn":[0.004773981195],"iteration":485,"passed_time":81.12541514,"remaining_time":85.79930737},
{"learn":[0.00476522861],"iteration":486,"passed_time":81.28147109,"remaining_time":85.62093362},
{"learn":[0.004753638388],"iteration":487,"passed_time":81.42103168,"remaining_time":85.42534472},
{"learn":[0.00473376304],"iteration":488,"passed_time":81.56064418,"remaining_time":85.23003921},
{"learn":[0.004724061671],"iteration":489,"passed_time":81.70503482,"remaining_time":85.0399342},
{"learn":[0.004712889389],"iteration":490,"passed_time":81.87651802,"remaining_time":84.87810117},
{"learn":[0.004703401942],"iteration":491,"passed_time":82.03003887,"remaining_time":84.69768241},
{"learn":[0.004689302096],"iteration":492,"passed_time":82.21051465,"remaining_time":84.54509316},
{"learn":[0.004683382395],"iteration":493,"passed_time":82.35626667,"remaining_time":84.35682375},
{"learn":[0.004667074397],"iteration":494,"passed_time":82.53894944,"remaining_time":84.20640296},
{"learn":[0.00464975938],"iteration":495,"passed_time":82.67826352,"remaining_time":84.0117839},
{"learn":[0.004636741426],"iteration":496,"passed_time":82.85757487,"remaining_time":83.85786752},
{"learn":[0.004624485272],"iteration":497,"passed_time":83.02893415,"remaining_time":83.69583322},
{"learn":[0.00461085962],"iteration":498,"passed_time":83.21364074,"remaining_time":83.54716234},
{"learn":[0.004604560801],"iteration":499,"passed_time":83.35384378,"remaining_time":83.35384378},
{"learn":[0.004592256316],"iteration":500,"passed_time":83.52586309,"remaining_time":83.19242651},
{"learn":[0.004580624498],"iteration":501,"passed_time":83.70984815,"remaining_time":83.04283741},
{"learn":[0.004566588432],"iteration":502,"passed_time":83.90308931,"remaining_time":82.90225723},
{"learn":[0.004557632225],"iteration":503,"passed_time":84.06707254,"remaining_time":82.73267456},
{"learn":[0.004546351794],"iteration":504,"passed_time":84.25262237,"remaining_time":82.58425361},
{"learn":[0.004534321447],"iteration":505,"passed_time":84.42273364,"remaining_time":82.42061347},
{"learn":[0.004523250976],"iteration":506,"passed_time":84.58970816,"remaining_time":82.25389768},
{"learn":[0.004514425895],"iteration":507,"passed_time":84.76127667,"remaining_time":82.09163016},
{"learn":[0.004505560803],"iteration":508,"passed_time":84.90798427,"remaining_time":81.90534436},
{"learn":[0.004465437725],"iteration":509,"passed_time":85.04809441,"remaining_time":81.71287503},
{"learn":[0.0044562054],"iteration":510,"passed_time":85.22151277,"remaining_time":81.55248483},
{"learn":[0.004444652812],"iteration":511,"passed_time":85.39778372,"remaining_time":81.3947626},
{"learn":[0.004437875837],"iteration":512,"passed_time":85.57640544,"remaining_time":81.23919971},
{"learn":[0.004426461903],"iteration":513,"passed_time":85.75961781,"remaining_time":81.08788766},
{"learn":[0.004414394317],"iteration":514,"passed_time":85.93992924,"remaining_time":80.93371977},
{"learn":[0.004404560237],"iteration":515,"passed_time":86.10674253,"remaining_time":80.7667895},
{"learn":[0.004395974828],"iteration":516,"passed_time":86.27206586,"remaining_time":80.59846772},
{"learn":[0.004383892981],"iteration":517,"passed_time":86.4498897,"remaining_time":80.44178926},
{"learn":[0.004365021483],"iteration":518,"passed_time":86.5894894,"remaining_time":80.24960386},
{"learn":[0.004356201948],"iteration":519,"passed_time":86.75372294,"remaining_time":80.08035964},
{"learn":[0.00434214251],"iteration":520,"passed_time":86.89328038,"remaining_time":79.8884478},
{"learn":[0.004330659248],"iteration":521,"passed_time":87.06434958,"remaining_time":79.72559214},
{"learn":[0.004320232525],"iteration":522,"passed_time":87.23944602,"remaining_time":79.56637811},
{"learn":[0.004309934154],"iteration":523,"passed_time":87.41986176,"remaining_time":79.41193549},
{"learn":[0.004300617449],"iteration":524,"passed_time":87.60536598,"remaining_time":79.26199779},
{"learn":[0.004291866053],"iteration":525,"passed_time":87.77378661,"remaining_time":79.09653013},
{"learn":[0.004280120142],"iteration":526,"passed_time":87.94551871,"remaining_time":78.93402344},
{"learn":[0.004269556746],"iteration":527,"passed_time":88.1129044,"remaining_time":78.76759635},
{"learn":[0.004262010445],"iteration":528,"passed_time":88.27258036,"remaining_time":78.59430123},
{"learn":[0.004253382252],"iteration":529,"passed_time":88.44202925,"remaining_time":78.42972405},
{"learn":[0.00424521716],"iteration":530,"passed_time":88.60135024,"remaining_time":78.25618317},
{"learn":[0.004234225524],"iteration":531,"passed_time":88.78910298,"remaining_time":78.10770714},
{"learn":[0.004226213347],"iteration":532,"passed_time":88.95809152,"remaining_time":77.94264304},
{"learn":[0.004214443668],"iteration":533,"passed_time":89.14350259,"remaining_time":77.79189552},
{"learn":[0.004205920851],"iteration":534,"passed_time":89.31520398,"remaining_time":77.62910252},
{"learn":[0.004196772511],"iteration":535,"passed_time":89.4852585,"remaining_time":77.46485064},
{"learn":[0.004181248498],"iteration":536,"passed_time":89.62776339,"remaining_time":77.27682393},
{"learn":[0.004171828397],"iteration":537,"passed_time":89.80837431,"remaining_time":77.12168947},
{"learn":[0.004161192505],"iteration":538,"passed_time":89.99763982,"remaining_time":76.97386263},
{"learn":[0.004155442753],"iteration":539,"passed_time":90.15376765,"remaining_time":76.79765393},
{"learn":[0.00414448162],"iteration":540,"passed_time":90.32988365,"remaining_time":76.638478},
{"learn":[0.004135122526],"iteration":541,"passed_time":90.50934852,"remaining_time":76.48206942},
{"learn":[0.00412840656],"iteration":542,"passed_time":90.65804828,"remaining_time":76.29968336},
{"learn":[0.004122381878],"iteration":543,"passed_time":90.80911369,"remaining_time":76.11940412},
{"learn":[0.00411314678],"iteration":544,"passed_time":90.99271755,"remaining_time":75.96639722},
{"learn":[0.004104508683],"iteration":545,"passed_time":91.16513233,"remaining_time":75.8039745},
{"learn":[0.004097755082],"iteration":546,"passed_time":91.33319824,"remaining_time":75.63791372},
{"learn":[0.004091432494],"iteration":547,"passed_time":91.47806056,"remaining_time":75.45270688},
{"learn":[0.004080445612],"iteration":548,"passed_time":91.66212748,"remaining_time":75.29985336},
{"learn":[0.004068126865],"iteration":549,"passed_time":91.86582158,"remaining_time":75.16294493},
{"learn":[0.00405575345],"iteration":550,"passed_time":92.00591725,"remaining_time":74.97396887},
{"learn":[0.004048188529],"iteration":551,"passed_time":92.16895266,"remaining_time":74.80378767},
{"learn":[0.004041997068],"iteration":552,"passed_time":92.32185572,"remaining_time":74.62544215},
{"learn":[0.00403268987],"iteration":553,"passed_time":92.48844504,"remaining_time":74.45820665},
{"learn":[0.004027030045],"iteration":554,"passed_time":92.63160773,"remaining_time":74.27218998},
{"learn":[0.004021245828],"iteration":555,"passed_time":92.78736065,"remaining_time":74.09638153},
{"learn":[0.004010657474],"iteration":556,"passed_time":92.96479446,"remaining_time":73.93788859},
{"learn":[0.004003583386],"iteration":557,"passed_time":93.11928795,"remaining_time":73.7611564},
{"learn":[0.003996735501],"iteration":558,"passed_time":93.28192509,"remaining_time":73.59092838},
{"learn":[0.0039775863],"iteration":559,"passed_time":93.42202509,"remaining_time":73.40301971},
{"learn":[0.003968417359],"iteration":560,"passed_time":93.58775202,"remaining_time":73.23533536},
{"learn":[0.00396006053],"iteration":561,"passed_time":93.74779521,"remaining_time":73.0632283},
{"learn":[0.00395131468],"iteration":562,"passed_time":93.91651169,"remaining_time":72.89789629},
{"learn":[0.003944402618],"iteration":563,"passed_time":94.06750298,"remaining_time":72.71884982},
{"learn":[0.003939112799],"iteration":564,"passed_time":94.22965241,"remaining_time":72.54849345},
{"learn":[0.003929341311],"iteration":565,"passed_time":94.4083559,"remaining_time":72.39085947},
{"learn":[0.00392133983],"iteration":566,"passed_time":94.56765888,"remaining_time":72.21833562},
{"learn":[0.00391216059],"iteration":567,"passed_time":94.74189167,"remaining_time":72.05721338},
{"learn":[0.00390371225],"iteration":568,"passed_time":94.91211053,"remaining_time":71.89300463},
{"learn":[0.003896400866],"iteration":569,"passed_time":95.07160225,"remaining_time":71.7206824},
{"learn":[0.003887628474],"iteration":570,"passed_time":95.24794638,"remaining_time":71.56106654},
{"learn":[0.0038763936],"iteration":571,"passed_time":95.38816273,"remaining_time":71.37435953},
{"learn":[0.003870558279],"iteration":572,"passed_time":95.55931589,"remaining_time":71.21086891},
{"learn":[0.003862287019],"iteration":573,"passed_time":95.73729683,"remaining_time":71.0524189},
{"learn":[0.003854463411],"iteration":574,"passed_time":95.9137839,"remaining_time":70.89279679},
{"learn":[0.003850131884],"iteration":575,"passed_time":96.06353406,"remaining_time":70.71343479},
{"learn":[0.003840190446],"iteration":576,"passed_time":96.25549709,"remaining_time":70.56512178},
{"learn":[0.003831200963],"iteration":577,"passed_time":96.40314495,"remaining_time":70.38430306},
{"learn":[0.003823806387],"iteration":578,"passed_time":96.56969904,"remaining_time":70.21734593},
{"learn":[0.003815822734],"iteration":579,"passed_time":96.73158211,"remaining_time":70.04700773},
{"learn":[0.003807839476],"iteration":580,"passed_time":96.91049953,"remaining_time":69.88898331},
{"learn":[0.003802864598],"iteration":581,"passed_time":97.04887141,"remaining_time":69.70176675},
{"learn":[0.003796881513],"iteration":582,"passed_time":97.18628926,"remaining_time":69.51403537},
{"learn":[0.003788627287],"iteration":583,"passed_time":97.35788736,"remaining_time":69.35082387},
{"learn":[0.003779679796],"iteration":584,"passed_time":97.49604887,"remaining_time":69.16386373},
{"learn":[0.00377207209],"iteration":585,"passed_time":97.66776061,"remaining_time":69.00077285},
{"learn":[0.003761963477],"iteration":586,"passed_time":97.859373,"remaining_time":68.85165425},
{"learn":[0.003742161417],"iteration":587,"passed_time":97.99789829,"remaining_time":68.66519404},
{"learn":[0.003734914211],"iteration":588,"passed_time":98.16580191,"remaining_time":68.49939658},
{"learn":[0.003716959804],"iteration":589,"passed_time":98.30685586,"remaining_time":68.31493373},
{"learn":[0.003706939533],"iteration":590,"passed_time":98.50364229,"remaining_time":68.1691873},
{"learn":[0.003700784121],"iteration":591,"passed_time":98.66690605,"remaining_time":68.00016498},
{"learn":[0.003689990957],"iteration":592,"passed_time":98.87748404,"remaining_time":67.86363575},
{"learn":[0.003682509228],"iteration":593,"passed_time":99.04938571,"remaining_time":67.70042188},
{"learn":[0.003674868642],"iteration":594,"passed_time":99.19992733,"remaining_time":67.52263961},
{"learn":[0.003669227436],"iteration":595,"passed_time":99.34994264,"remaining_time":67.34459199},
{"learn":[0.003661721938],"iteration":596,"passed_time":99.50897222,"remaining_time":67.17272329},
{"learn":[0.00365256409],"iteration":597,"passed_time":99.69044229,"remaining_time":67.01598295},
{"learn":[0.003642528764],"iteration":598,"passed_time":99.88623861,"remaining_time":66.86875072},
{"learn":[0.003635190047],"iteration":599,"passed_time":100.0573697,"remaining_time":66.70491316},
{"learn":[0.003626855402],"iteration":600,"passed_time":100.2377489,"remaining_time":66.54719106},
{"learn":[0.003617129075],"iteration":601,"passed_time":100.4183605,"remaining_time":66.38954733},
{"learn":[0.003612156178],"iteration":602,"passed_time":100.5820906,"remaining_time":66.22071307},
{"learn":[0.003603627023],"iteration":603,"passed_time":100.765675,"remaining_time":66.06491278},
{"learn":[0.003595664365],"iteration":604,"passed_time":100.9427524,"remaining_time":65.90477222},
{"learn":[0.003587067865],"iteration":605,"passed_time":101.1264913,"remaining_time":65.74890686},
{"learn":[0.003580284948],"iteration":606,"passed_time":101.2869036,"remaining_time":65.57784699},
{"learn":[0.003572464509],"iteration":607,"passed_time":101.4639558,"remaining_time":65.41755048},
{"learn":[0.003565443901],"iteration":608,"passed_time":101.625158,"remaining_time":65.24702262},
{"learn":[0.003560346216],"iteration":609,"passed_time":101.7893707,"remaining_time":65.07845011},
{"learn":[0.003550905119],"iteration":610,"passed_time":101.99441,"remaining_time":64.93588458},
{"learn":[0.003544847557],"iteration":611,"passed_time":102.1694181,"remaining_time":64.77407553},
{"learn":[0.003535284445],"iteration":612,"passed_time":102.3620795,"remaining_time":64.62336831},
{"learn":[0.003527667232],"iteration":613,"passed_time":102.5720146,"remaining_time":64.48338376},
{"learn":[0.003520279787],"iteration":614,"passed_time":102.749961,"remaining_time":64.3231463},
{"learn":[0.00351448844],"iteration":615,"passed_time":102.9105939,"remaining_time":64.15205853},
{"learn":[0.003510297943],"iteration":616,"passed_time":103.0550557,"remaining_time":63.97096653},
{"learn":[0.003502397877],"iteration":617,"passed_time":103.2437703,"remaining_time":63.81734666},
{"learn":[0.003495643484],"iteration":618,"passed_time":103.4185774,"remaining_time":63.65505327},
{"learn":[0.003490037931],"iteration":619,"passed_time":103.5914279,"remaining_time":63.49152034},
{"learn":[0.003480852748],"iteration":620,"passed_time":103.7939394,"remaining_time":63.34605966},
{"learn":[0.003461344237],"iteration":621,"passed_time":103.9344443,"remaining_time":63.16273302},
{"learn":[0.003456354701],"iteration":622,"passed_time":104.0872197,"remaining_time":62.9869692},
{"learn":[0.003449775803],"iteration":623,"passed_time":104.2605403,"remaining_time":62.82365889},
{"learn":[0.003427222467],"iteration":624,"passed_time":104.3976606,"remaining_time":62.63859639},
{"learn":[0.003421459246],"iteration":625,"passed_time":104.5644337,"remaining_time":62.47140287},
{"learn":[0.003415499138],"iteration":626,"passed_time":104.7298595,"remaining_time":62.30340925},
{"learn":[0.003408723352],"iteration":627,"passed_time":104.902244,"remaining_time":62.1395458},
{"learn":[0.003403259226],"iteration":628,"passed_time":105.0705733,"remaining_time":61.97326341},
{"learn":[0.003397677046],"iteration":629,"passed_time":105.237339,"remaining_time":61.80605627},
{"learn":[0.00339026821],"iteration":630,"passed_time":105.4128253,"remaining_time":61.64395016},
{"learn":[0.003383483312],"iteration":631,"passed_time":105.5851027,"remaining_time":61.47993322},
{"learn":[0.003378971536],"iteration":632,"passed_time":105.7263578,"remaining_time":61.29790415},
{"learn":[0.003373914258],"iteration":633,"passed_time":105.8924443,"remaining_time":61.1303385},
{"learn":[0.003366228511],"iteration":634,"passed_time":106.0896875,"remaining_time":60.98068653},
{"learn":[0.003360767158],"iteration":635,"passed_time":106.2521118,"remaining_time":60.81095705},
{"learn":[0.003355282036],"iteration":636,"passed_time":106.4245929,"remaining_time":60.64698148},
{"learn":[0.003348478915],"iteration":637,"passed_time":106.6008258,"remaining_time":60.48510803},
{"learn":[0.003341486434],"iteration":638,"passed_time":106.7922421,"remaining_time":60.33176745},
{"learn":[0.003334039171],"iteration":639,"passed_time":106.9809245,"remaining_time":60.17677004},
{"learn":[0.003326160498],"iteration":640,"passed_time":107.1702791,"remaining_time":60.02204397},
{"learn":[0.003320541278],"iteration":641,"passed_time":107.3410093,"remaining_time":59.85682451},
{"learn":[0.003297713606],"iteration":642,"passed_time":107.4819648,"remaining_time":59.67505664},
{"learn":[0.003291661789],"iteration":643,"passed_time":107.6588667,"remaining_time":59.51328657},
{"learn":[0.003287240929],"iteration":644,"passed_time":107.8091786,"remaining_time":59.33683471},
{"learn":[0.003281343017],"iteration":645,"passed_time":107.9751012,"remaining_time":59.16901829},
{"learn":[0.003275171759],"iteration":646,"passed_time":108.1492055,"remaining_time":59.00567164},
{"learn":[0.003268282872],"iteration":647,"passed_time":108.3358193,"remaining_time":58.84908703},
{"learn":[0.003263969567],"iteration":648,"passed_time":108.4957658,"remaining_time":58.67798733},
{"learn":[0.003246485394],"iteration":649,"passed_time":108.6360588,"remaining_time":58.49633934},
{"learn":[0.003240133491],"iteration":650,"passed_time":108.8190145,"remaining_time":58.3376898},
{"learn":[0.003233588662],"iteration":651,"passed_time":109.0093636,"remaining_time":58.18291187},
{"learn":[0.003226470997],"iteration":652,"passed_time":109.1882883,"remaining_time":58.02195413},
{"learn":[0.003222542554],"iteration":653,"passed_time":109.3446076,"remaining_time":57.84898201},
{"learn":[0.003216262355],"iteration":654,"passed_time":109.5434793,"remaining_time":57.69847383},
{"learn":[0.003212301626],"iteration":655,"passed_time":109.7005762,"remaining_time":57.5259119},
{"learn":[0.00320610759],"iteration":656,"passed_time":109.875223,"remaining_time":57.36255934},
{"learn":[0.003200764488],"iteration":657,"passed_time":110.0571032,"remaining_time":57.20293204},
{"learn":[0.003188124661],"iteration":658,"passed_time":110.1984154,"remaining_time":57.0222453},
{"learn":[0.003181574087],"iteration":659,"passed_time":110.3986259,"remaining_time":56.87201939},
{"learn":[0.003174083445],"iteration":660,"passed_time":110.6010955,"remaining_time":56.72280089},
{"learn":[0.003167799086],"iteration":661,"passed_time":110.7737062,"remaining_time":56.55817627},
{"learn":[0.003163143308],"iteration":662,"passed_time":110.9448635,"remaining_time":56.39278886},
{"learn":[0.00315761659],"iteration":663,"passed_time":111.1186953,"remaining_time":56.22873736},
{"learn":[0.003152907134],"iteration":664,"passed_time":111.2793521,"remaining_time":56.05801945},
{"learn":[0.003149557271],"iteration":665,"passed_time":111.4272413,"remaining_time":55.88092883},
{"learn":[0.003145016378],"iteration":666,"passed_time":111.595078,"remaining_time":55.71388454},
{"learn":[0.003131477879],"iteration":667,"passed_time":111.7376616,"remaining_time":55.53428689},
{"learn":[0.003125531042],"iteration":668,"passed_time":111.90607,"remaining_time":55.36757726},
{"learn":[0.003120964002],"iteration":669,"passed_time":112.0724025,"remaining_time":55.19984001},
{"learn":[0.00311416009],"iteration":670,"passed_time":112.2718249,"remaining_time":55.04833144},
{"learn":[0.003109952558],"iteration":671,"passed_time":112.4375985,"remaining_time":54.88025639},
{"learn":[0.003105752157],"iteration":672,"passed_time":112.5887394,"remaining_time":54.70507842},
{"learn":[0.003099832852],"iteration":673,"passed_time":112.7787244,"remaining_time":54.54875989},
{"learn":[0.003080931445],"iteration":674,"passed_time":112.9159253,"remaining_time":54.36692698},
{"learn":[0.003076384213],"iteration":675,"passed_time":113.0715985,"remaining_time":54.19407975},
{"learn":[0.003051325809],"iteration":676,"passed_time":113.2126525,"remaining_time":54.01430835},
{"learn":[0.00304527716],"iteration":677,"passed_time":113.3772324,"remaining_time":53.84582424},
{"learn":[0.003042073874],"iteration":678,"passed_time":113.5231542,"remaining_time":53.66853094},
{"learn":[0.003038736689],"iteration":679,"passed_time":113.6808796,"remaining_time":53.49688453},
{"learn":[0.003033273751],"iteration":680,"passed_time":113.8647543,"remaining_time":53.3375281},
{"learn":[0.003026590863],"iteration":681,"passed_time":114.0595471,"remaining_time":53.18319058},
{"learn":[0.00302213633],"iteration":682,"passed_time":114.2268864,"remaining_time":53.01599266},
{"learn":[0.003016575147],"iteration":683,"passed_time":114.4028716,"remaining_time":52.85278865},
{"learn":[0.00301088363],"iteration":684,"passed_time":114.5710957,"remaining_time":52.68597833},
{"learn":[0.003005115259],"iteration":685,"passed_time":114.7546904,"remaining_time":52.52619941},
{"learn":[0.002998343038],"iteration":686,"passed_time":114.957938,"remaining_time":52.37530508},
{"learn":[0.002992673903],"iteration":687,"passed_time":115.152361,"remaining_time":52.22025675},
{"learn":[0.002988667617],"iteration":688,"passed_time":115.3126703,"remaining_time":52.04969588},
{"learn":[0.002983647379],"iteration":689,"passed_time":115.4830096,"remaining_time":51.883671},
{"learn":[0.002978950204],"iteration":690,"passed_time":115.6621789,"remaining_time":51.72158215},
{"learn":[0.002974284324],"iteration":691,"passed_time":115.824774,"remaining_time":51.55206705},
{"learn":[0.002969915559],"iteration":692,"passed_time":115.9984617,"remaining_time":51.38748593},
{"learn":[0.002964813516],"iteration":693,"passed_time":116.1623865,"remaining_time":51.21857388},
{"learn":[0.002961833263],"iteration":694,"passed_time":116.3160549,"remaining_time":51.04517518},
{"learn":[0.002959633431],"iteration":695,"passed_time":116.4626484,"remaining_time":50.86874299},
{"learn":[0.002954243187],"iteration":696,"passed_time":116.6317014,"remaining_time":50.70216},
{"learn":[0.002949214234],"iteration":697,"passed_time":116.8094308,"remaining_time":50.53932393},
{"learn":[0.002944179735],"iteration":698,"passed_time":116.9805079,"remaining_time":50.37358064},
{"learn":[0.002940795803],"iteration":699,"passed_time":117.1261387,"remaining_time":50.19691658},
{"learn":[0.002935668803],"iteration":700,"passed_time":117.3032437,"remaining_time":50.03376586},
{"learn":[0.002931022335],"iteration":701,"passed_time":117.4460066,"remaining_time":49.85599711},
{"learn":[0.002928255014],"iteration":702,"passed_time":117.5922513,"remaining_time":49.67979889},
{"learn":[0.002925240494],"iteration":703,"passed_time":117.7405378,"remaining_time":49.50454431},
{"learn":[0.002921310467],"iteration":704,"passed_time":117.8917697,"remaining_time":49.33059868},
{"learn":[0.002918510464],"iteration":705,"passed_time":118.0415097,"remaining_time":49.15609613},
{"learn":[0.002906130116],"iteration":706,"passed_time":118.1790029,"remaining_time":48.97658821},
{"learn":[0.002902349835],"iteration":707,"passed_time":118.3428341,"remaining_time":48.80806154},
{"learn":[0.002897695048],"iteration":708,"passed_time":118.5236638,"remaining_time":48.64652493},
{"learn":[0.002893315784],"iteration":709,"passed_time":118.6957439,"remaining_time":48.48136019},
{"learn":[0.002888332388],"iteration":710,"passed_time":118.8730501,"remaining_time":48.31830026},
{"learn":[0.002882955614],"iteration":711,"passed_time":119.0568093,"remaining_time":48.15781049},
{"learn":[0.002877093751],"iteration":712,"passed_time":119.2441953,"remaining_time":47.99871538},
{"learn":[0.00287153435],"iteration":713,"passed_time":119.4272181,"remaining_time":47.83779322},
{"learn":[0.002867740204],"iteration":714,"passed_time":119.5837296,"remaining_time":47.66624186},
{"learn":[0.002863243679],"iteration":715,"passed_time":119.7560773,"remaining_time":47.50101388},
{"learn":[0.002857639117],"iteration":716,"passed_time":119.955534,"remaining_time":47.34646602},
{"learn":[0.002852394657],"iteration":717,"passed_time":120.1391516,"remaining_time":47.18557207},
{"learn":[0.002846948358],"iteration":718,"passed_time":120.3129059,"remaining_time":47.02076017},
{"learn":[0.002842764595],"iteration":719,"passed_time":120.4893167,"remaining_time":46.85695651},
{"learn":[0.002837962043],"iteration":720,"passed_time":120.6701192,"remaining_time":46.69481729},
{"learn":[0.00283442282],"iteration":721,"passed_time":120.8318876,"remaining_time":46.52529746},
{"learn":[0.002830603716],"iteration":722,"passed_time":121.0100986,"remaining_time":46.36209865},
{"learn":[0.002826842846],"iteration":723,"passed_time":121.1835037,"remaining_time":46.19702629},
{"learn":[0.002822142897],"iteration":724,"passed_time":121.3559053,"remaining_time":46.0315503},
{"learn":[0.002819672096],"iteration":725,"passed_time":121.5041336,"remaining_time":45.85693195},
{"learn":[0.002816451578],"iteration":726,"passed_time":121.6680966,"remaining_time":45.68829489},
{"learn":[0.002812981285],"iteration":727,"passed_time":121.8287948,"remaining_time":45.51845081},
{"learn":[0.002809147721],"iteration":728,"passed_time":121.995987,"remaining_time":45.35104592},
{"learn":[0.002799335429],"iteration":729,"passed_time":122.1377328,"remaining_time":45.17422995},
{"learn":[0.002792599853],"iteration":730,"passed_time":122.2840175,"remaining_time":44.99918018},
{"learn":[0.002788690426],"iteration":731,"passed_time":122.4430634,"remaining_time":44.82888115},
{"learn":[0.002785783066],"iteration":732,"passed_time":122.6062516,"remaining_time":44.66012166},
{"learn":[0.002781068657],"iteration":733,"passed_time":122.7461622,"remaining_time":44.48294163},
{"learn":[0.002776711776],"iteration":734,"passed_time":122.9202424,"remaining_time":44.31818263},
{"learn":[0.002766952965],"iteration":735,"passed_time":123.058705,"remaining_time":44.14062245},
{"learn":[0.002763135049],"iteration":736,"passed_time":123.2171549,"remaining_time":43.97030086},
{"learn":[0.002758177007],"iteration":737,"passed_time":123.3908535,"remaining_time":43.80542494},
{"learn":[0.002752766164],"iteration":738,"passed_time":123.5820833,"remaining_time":43.64671683},
{"learn":[0.00274850634],"iteration":739,"passed_time":123.7403937,"remaining_time":43.47635453},
{"learn":[0.002745486869],"iteration":740,"passed_time":123.9048913,"remaining_time":43.30818737},
{"learn":[0.00274017843],"iteration":741,"passed_time":124.0956022,"remaining_time":43.1491447},
{"learn":[0.002736109354],"iteration":742,"passed_time":124.2673634,"remaining_time":42.98346216},
{"learn":[0.002731099416],"iteration":743,"passed_time":124.4676468,"remaining_time":42.82757738},
{"learn":[0.002728266731],"iteration":744,"passed_time":124.6150661,"remaining_time":42.65347902},
{"learn":[0.002724163981],"iteration":745,"passed_time":124.7997379,"remaining_time":42.49213596},
{"learn":[0.002718897535],"iteration":746,"passed_time":124.9947393,"remaining_time":42.33422897},
{"learn":[0.002715344249],"iteration":747,"passed_time":125.1392869,"remaining_time":42.15922499},
{"learn":[0.002712253074],"iteration":748,"passed_time":125.2903675,"remaining_time":41.98649163},
{"learn":[0.002707624432],"iteration":749,"passed_time":125.4644947,"remaining_time":41.82149825},
{"learn":[0.002703900999],"iteration":750,"passed_time":125.6242388,"remaining_time":41.65171167},
{"learn":[0.002699317321],"iteration":751,"passed_time":125.8079459,"remaining_time":41.48985449},
{"learn":[0.002694120597],"iteration":752,"passed_time":125.991421,"remaining_time":41.32786318},
{"learn":[0.002691753588],"iteration":753,"passed_time":126.1490074,"remaining_time":41.15736847},
{"learn":[0.002688751151],"iteration":754,"passed_time":126.3047455,"remaining_time":40.98630813},
{"learn":[0.002683473811],"iteration":755,"passed_time":126.4990916,"remaining_time":40.82774915},
{"learn":[0.002678981446],"iteration":756,"passed_time":126.682097,"remaining_time":40.66545519},
{"learn":[0.002673161179],"iteration":757,"passed_time":126.8235508,"remaining_time":40.48984077},
{"learn":[0.002667735084],"iteration":758,"passed_time":127.0276125,"remaining_time":40.3341958},
{"learn":[0.002663254999],"iteration":759,"passed_time":127.1942495,"remaining_time":40.1666051},
{"learn":[0.002659342997],"iteration":760,"passed_time":127.334203,"remaining_time":39.99063669},
{"learn":[0.002651468682],"iteration":761,"passed_time":127.4767464,"remaining_time":39.8155717},
{"learn":[0.002647118139],"iteration":762,"passed_time":127.660196,"remaining_time":39.6532981},
{"learn":[0.002644100847],"iteration":763,"passed_time":127.8239412,"remaining_time":39.48488237},
{"learn":[0.00263950053],"iteration":764,"passed_time":128.0144414,"remaining_time":39.32469769},
{"learn":[0.002636088274],"iteration":765,"passed_time":128.1863317,"remaining_time":39.15874884},
{"learn":[0.002633290053],"iteration":766,"passed_time":128.3445777,"remaining_time":38.98863965},
{"learn":[0.002630112913],"iteration":767,"passed_time":128.5143604,"remaining_time":38.82204636},
{"learn":[0.002625673039],"iteration":768,"passed_time":128.6862803,"remaining_time":38.6560868},
{"learn":[0.002622425186],"iteration":769,"passed_time":128.825177,"remaining_time":38.48024768},
{"learn":[0.002616247986],"iteration":770,"passed_time":128.964355,"remaining_time":38.30458793},
{"learn":[0.002612709159],"iteration":771,"passed_time":129.1276953,"remaining_time":38.13615871},
{"learn":[0.002608761305],"iteration":772,"passed_time":129.2987757,"remaining_time":37.97001565},
{"learn":[0.002606130063],"iteration":773,"passed_time":129.4529114,"remaining_time":37.79891212},
{"learn":[0.002604130089],"iteration":774,"passed_time":129.602764,"remaining_time":37.6266089},
{"learn":[0.00260022185],"iteration":775,"passed_time":129.7842544,"remaining_time":37.46349611},
{"learn":[0.00259572691],"iteration":776,"passed_time":129.972987,"remaining_time":37.30241453},
{"learn":[0.002592174416],"iteration":777,"passed_time":130.1142629,"remaining_time":37.12772027},
{"learn":[0.002589158312],"iteration":778,"passed_time":130.2808974,"remaining_time":36.96030593},
{"learn":[0.002584522738],"iteration":779,"passed_time":130.4774456,"remaining_time":36.80133081},
{"learn":[0.002580555671],"iteration":780,"passed_time":130.6554428,"remaining_time":36.63705757},
{"learn":[0.002576068852],"iteration":781,"passed_time":130.8469948,"remaining_time":36.47652797},
{"learn":[0.00257257895],"iteration":782,"passed_time":131.0148832,"remaining_time":36.30936099},
{"learn":[0.002568739839],"iteration":783,"passed_time":131.159655,"remaining_time":36.13582331},
{"learn":[0.002565039383],"iteration":784,"passed_time":131.3327308,"remaining_time":35.97011098},
{"learn":[0.002561714082],"iteration":785,"passed_time":131.5078926,"remaining_time":35.80494786},
{"learn":[0.002558795035],"iteration":786,"passed_time":131.6811613,"remaining_time":35.63924696},
{"learn":[0.002555220752],"iteration":787,"passed_time":131.8636605,"remaining_time":35.47601018},
{"learn":[0.00255139214],"iteration":788,"passed_time":132.0275091,"remaining_time":35.30773691},
{"learn":[0.002548383365],"iteration":789,"passed_time":132.2011902,"remaining_time":35.14208855},
{"learn":[0.002546087069],"iteration":790,"passed_time":132.3558095,"remaining_time":34.9713833},
{"learn":[0.002542763551],"iteration":791,"passed_time":132.5195336,"remaining_time":34.80310985},
{"learn":[0.002538770536],"iteration":792,"passed_time":132.6953547,"remaining_time":34.63800559},
{"learn":[0.00253564648],"iteration":793,"passed_time":132.8642939,"remaining_time":34.47108884},
{"learn":[0.002526523691],"iteration":794,"passed_time":133.0076721,"remaining_time":34.29757581},
{"learn":[0.002524078244],"iteration":795,"passed_time":133.1514022,"remaining_time":34.1242287},
{"learn":[0.002521636363],"iteration":796,"passed_time":133.3042947,"remaining_time":33.95328962},
{"learn":[0.002518445754],"iteration":797,"passed_time":133.4750287,"remaining_time":33.78691203},
{"learn":[0.002514407973],"iteration":798,"passed_time":133.6590993,"remaining_time":33.62387855},
{"learn":[0.00251077407],"iteration":799,"passed_time":133.8359666,"remaining_time":33.45899166},
{"learn":[0.002508188979],"iteration":800,"passed_time":133.9869346,"remaining_time":33.28764042},
{"learn":[0.002504673921],"iteration":801,"passed_time":134.1515053,"remaining_time":33.11969832},
{"learn":[0.002501307619],"iteration":802,"passed_time":134.2933382,"remaining_time":32.94618634},
{"learn":[0.00249754556],"iteration":803,"passed_time":134.4671341,"remaining_time":32.78054514},
{"learn":[0.00248914872],"iteration":804,"passed_time":134.6047171,"remaining_time":32.6061116},
{"learn":[0.00248608686],"iteration":805,"passed_time":134.7698662,"remaining_time":32.43840451},
{"learn":[0.002482370756],"iteration":806,"passed_time":134.9418947,"remaining_time":32.27234904},
{"learn":[0.002478799048],"iteration":807,"passed_time":135.1179986,"remaining_time":32.10724719},
{"learn":[0.002475275671],"iteration":808,"passed_time":135.3010394,"remaining_time":31.9437559},
{"learn":[0.002473206767],"iteration":809,"passed_time":135.4470447,"remaining_time":31.77152899},
{"learn":[0.002469696661],"iteration":810,"passed_time":135.6244734,"remaining_time":31.60668985},
{"learn":[0.002467486528],"iteration":811,"passed_time":135.7772437,"remaining_time":31.43611061},
{"learn":[0.002463706049],"iteration":812,"passed_time":135.9675655,"remaining_time":31.27421248},
{"learn":[0.00245247474],"iteration":813,"passed_time":136.1043266,"remaining_time":31.10000582},
{"learn":[0.002446662],"iteration":814,"passed_time":136.2434783,"remaining_time":30.92643373},
{"learn":[0.002439925433],"iteration":815,"passed_time":136.3891136,"remaining_time":30.75440797},
{"learn":[0.002436216261],"iteration":816,"passed_time":136.5605899,"remaining_time":30.58823494},
{"learn":[0.002433168069],"iteration":817,"passed_time":136.7222207,"remaining_time":30.41985839},
{"learn":[0.002429927941],"iteration":818,"passed_time":136.8911894,"remaining_time":30.25312},
{"learn":[0.002426212232],"iteration":819,"passed_time":137.0772246,"remaining_time":30.09012248},
{"learn":[0.002422570405],"iteration":820,"passed_time":137.2505957,"remaining_time":29.92430771},
{"learn":[0.002419385937],"iteration":821,"passed_time":137.416495,"remaining_time":29.75685658},
{"learn":[0.002417008232],"iteration":822,"passed_time":137.5576866,"remaining_time":29.58409541},
{"learn":[0.002408735387],"iteration":823,"passed_time":137.6976716,"remaining_time":29.41115315},
{"learn":[0.002405892401],"iteration":824,"passed_time":137.8654015,"remaining_time":29.24417608},
{"learn":[0.002402100037],"iteration":825,"passed_time":138.0108982,"remaining_time":29.07251367},
{"learn":[0.002399009258],"iteration":826,"passed_time":138.1890475,"remaining_time":28.90774512},
{"learn":[0.002395985429],"iteration":827,"passed_time":138.360341,"remaining_time":28.74152012},
{"learn":[0.002393362902],"iteration":828,"passed_time":138.5122154,"remaining_time":28.57127723},
{"learn":[0.002390275689],"iteration":829,"passed_time":138.6778329,"remaining_time":28.40389348},
{"learn":[0.002387749229],"iteration":830,"passed_time":138.8367504,"remaining_time":28.23515141},
{"learn":[0.00238478918],"iteration":831,"passed_time":139.0111895,"remaining_time":28.0695671},
{"learn":[0.002380286911],"iteration":832,"passed_time":139.2006663,"remaining_time":27.90697632},
{"learn":[0.002376053234],"iteration":833,"passed_time":139.3810934,"remaining_time":27.74251978},
{"learn":[0.002372875896],"iteration":834,"passed_time":139.5524405,"remaining_time":27.57623077},
{"learn":[0.00236972926],"iteration":835,"passed_time":139.7282421,"remaining_time":27.41080346},
{"learn":[0.002367134859],"iteration":836,"passed_time":139.8841619,"remaining_time":27.24147955},
{"learn":[0.00236355206],"iteration":837,"passed_time":140.086506,"remaining_time":27.08116226},
{"learn":[0.002359801093],"iteration":838,"passed_time":140.2769661,"remaining_time":26.9184643},
{"learn":[0.002357818352],"iteration":839,"passed_time":140.4282033,"remaining_time":26.74822919},
{"learn":[0.002355335667],"iteration":840,"passed_time":140.572072,"remaining_time":26.5766462},
{"learn":[0.002352117921],"iteration":841,"passed_time":140.7432499,"remaining_time":26.41025355},
{"learn":[0.002349718626],"iteration":842,"passed_time":140.9021953,"remaining_time":26.24157137},
{"learn":[0.002334582446],"iteration":843,"passed_time":141.0399751,"remaining_time":26.06900014},
{"learn":[0.002330905758],"iteration":844,"passed_time":141.2178324,"remaining_time":25.90386276},
{"learn":[0.002328067922],"iteration":845,"passed_time":141.3880665,"remaining_time":25.73730762},
{"learn":[0.002324168003],"iteration":846,"passed_time":141.5789877,"remaining_time":25.57448066},
{"learn":[0.002322280932],"iteration":847,"passed_time":141.7414413,"remaining_time":25.40648475},
{"learn":[0.002318680306],"iteration":848,"passed_time":141.9247757,"remaining_time":25.24221571},
{"learn":[0.002314831688],"iteration":849,"passed_time":142.1150273,"remaining_time":25.07912247},
{"learn":[0.002311881543],"iteration":850,"passed_time":142.2666583,"remaining_time":24.90920339},
{"learn":[0.002308824239],"iteration":851,"passed_time":142.4503343,"remaining_time":24.74489376},
{"learn":[0.002305634819],"iteration":852,"passed_time":142.6388487,"remaining_time":24.58137252},
{"learn":[0.002302443813],"iteration":853,"passed_time":142.8307701,"remaining_time":24.41837521},
{"learn":[0.002288030017],"iteration":854,"passed_time":142.9695669,"remaining_time":24.24630082},
{"learn":[0.002284054036],"iteration":855,"passed_time":143.1083786,"remaining_time":24.07430668},
{"learn":[0.002281232443],"iteration":856,"passed_time":143.2709137,"remaining_time":23.90634849},
{"learn":[0.0022781173],"iteration":857,"passed_time":143.4467983,"remaining_time":23.74061231},
{"learn":[0.00227584101],"iteration":858,"passed_time":143.6130212,"remaining_time":23.57326657},
{"learn":[0.002272957815],"iteration":859,"passed_time":143.8032328,"remaining_time":23.40982859},
{"learn":[0.002269344908],"iteration":860,"passed_time":143.9964165,"remaining_time":23.24680824},
{"learn":[0.00226725679],"iteration":861,"passed_time":144.1493898,"remaining_time":23.07728051},
{"learn":[0.002264328038],"iteration":862,"passed_time":144.3353815,"remaining_time":22.91303275},
{"learn":[0.002261580525],"iteration":863,"passed_time":144.5027263,"remaining_time":22.74579951},
{"learn":[0.00225972574],"iteration":864,"passed_time":144.6491339,"remaining_time":22.57529836},
{"learn":[0.002254221009],"iteration":865,"passed_time":144.7915445,"remaining_time":22.40423436},
{"learn":[0.002251216789],"iteration":866,"passed_time":144.9720527,"remaining_time":22.23908075},
{"learn":[0.002249180765],"iteration":867,"passed_time":145.1268436,"remaining_time":22.06998082},
{"learn":[0.002247353118],"iteration":868,"passed_time":145.2852154,"remaining_time":21.90145365},
{"learn":[0.002243726147],"iteration":869,"passed_time":145.4729767,"remaining_time":21.73734134},
{"learn":[0.002240493149],"iteration":870,"passed_time":145.6585558,"remaining_time":21.57285155},
{"learn":[0.002237634516],"iteration":871,"passed_time":145.8450063,"remaining_time":21.40844129},
{"learn":[0.002234532051],"iteration":872,"passed_time":146.034781,"remaining_time":21.24446412},
{"learn":[0.00223198816],"iteration":873,"passed_time":146.2056138,"remaining_time":21.07769718},
{"learn":[0.002229964615],"iteration":874,"passed_time":146.3589947,"remaining_time":20.90842781},
{"learn":[0.002227394182],"iteration":875,"passed_time":146.5271073,"remaining_time":20.74128003},
{"learn":[0.00222394647],"iteration":876,"passed_time":146.7210077,"remaining_time":20.5777468},
{"learn":[0.002221068425],"iteration":877,"passed_time":146.8940545,"remaining_time":20.41124675},
{"learn":[0.002218217516],"iteration":878,"passed_time":147.0611714,"remaining_time":20.24391552},
{"learn":[0.002215481095],"iteration":879,"passed_time":147.2074003,"remaining_time":20.0737364},
{"learn":[0.002213757239],"iteration":880,"passed_time":147.3741577,"remaining_time":19.90638452},
{"learn":[0.002211537797],"iteration":881,"passed_time":147.5439873,"remaining_time":19.73944501},
{"learn":[0.002208938247],"iteration":882,"passed_time":147.714551,"remaining_time":19.57259622},
{"learn":[0.002205845686],"iteration":883,"passed_time":147.8896819,"remaining_time":19.40633835},
{"learn":[0.002198426747],"iteration":884,"passed_time":148.0291869,"remaining_time":19.23543107},
{"learn":[0.002195502748],"iteration":885,"passed_time":148.1983351,"remaining_time":19.0684088},
{"learn":[0.00219233987],"iteration":886,"passed_time":148.3856101,"remaining_time":18.90369103},
{"learn":[0.002189860354],"iteration":887,"passed_time":148.5257672,"remaining_time":18.73297965},
{"learn":[0.002186356784],"iteration":888,"passed_time":148.7248739,"remaining_time":18.56969742},
{"learn":[0.002183143396],"iteration":889,"passed_time":148.9106468,"remaining_time":18.40468669},
{"learn":[0.002180312295],"iteration":890,"passed_time":149.0766287,"remaining_time":18.23720822},
{"learn":[0.002177899333],"iteration":891,"passed_time":149.257041,"remaining_time":18.0714803},
{"learn":[0.002175043868],"iteration":892,"passed_time":149.4389515,"remaining_time":17.90589901},
{"learn":[0.002172101647],"iteration":893,"passed_time":149.6256798,"remaining_time":17.74085241},
{"learn":[0.002169899833],"iteration":894,"passed_time":149.7802972,"remaining_time":17.57199017},
{"learn":[0.002166523429],"iteration":895,"passed_time":149.9867574,"remaining_time":17.4091772},
{"learn":[0.002164267937],"iteration":896,"passed_time":150.1481892,"remaining_time":17.24109642},
{"learn":[0.002161875178],"iteration":897,"passed_time":150.3132974,"remaining_time":17.07344804},
{"learn":[0.002160012471],"iteration":898,"passed_time":150.459058,"remaining_time":16.90363165},
{"learn":[0.002157475314],"iteration":899,"passed_time":150.6301755,"remaining_time":16.73668617},
{"learn":[0.002154399787],"iteration":900,"passed_time":150.8139943,"remaining_time":16.57112701},
{"learn":[0.002150158385],"iteration":901,"passed_time":150.961926,"remaining_time":16.40162832},
{"learn":[0.002147681048],"iteration":902,"passed_time":151.1375807,"remaining_time":16.23515541},
{"learn":[0.002144616217],"iteration":903,"passed_time":151.2821788,"remaining_time":16.06536412},
{"learn":[0.002141984974],"iteration":904,"passed_time":151.4541692,"remaining_time":15.89850395},
{"learn":[0.002139479708],"iteration":905,"passed_time":151.6216966,"remaining_time":15.73116941},
{"learn":[0.002135740231],"iteration":906,"passed_time":151.8177089,"remaining_time":15.56675516},
{"learn":[0.002132733832],"iteration":907,"passed_time":152.0132034,"remaining_time":15.40221885},
{"learn":[0.002129786658],"iteration":908,"passed_time":152.2002422,"remaining_time":15.23676792},
{"learn":[0.002127609406],"iteration":909,"passed_time":152.3725485,"remaining_time":15.06981249},
{"learn":[0.002125271713],"iteration":910,"passed_time":152.5260051,"remaining_time":14.90100379},
{"learn":[0.002122047035],"iteration":911,"passed_time":152.7184526,"remaining_time":14.73599104},
{"learn":[0.002118617942],"iteration":912,"passed_time":152.8995703,"remaining_time":14.56983857},
{"learn":[0.002116177645],"iteration":913,"passed_time":153.0606448,"remaining_time":14.40176746},
{"learn":[0.002114147167],"iteration":914,"passed_time":153.2183864,"remaining_time":14.23340202},
{"learn":[0.002111968529],"iteration":915,"passed_time":153.3765293,"remaining_time":14.06509657},
{"learn":[0.002108973421],"iteration":916,"passed_time":153.5608651,"remaining_time":13.89918408},
{"learn":[0.002102390561],"iteration":917,"passed_time":153.6983239,"remaining_time":13.72904419},
{"learn":[0.002099675136],"iteration":918,"passed_time":153.8724557,"remaining_time":13.56220773},
{"learn":[0.002096767776],"iteration":919,"passed_time":154.0338776,"remaining_time":13.39425023},
{"learn":[0.002094802267],"iteration":920,"passed_time":154.1970637,"remaining_time":13.22645824},
{"learn":[0.00209190283],"iteration":921,"passed_time":154.3847159,"remaining_time":13.06074603},
{"learn":[0.002089809166],"iteration":922,"passed_time":154.5366553,"remaining_time":12.892007},
{"learn":[0.002086584884],"iteration":923,"passed_time":154.7315746,"remaining_time":12.72683947},
{"learn":[0.002082052508],"iteration":924,"passed_time":154.8693573,"remaining_time":12.55697491},
{"learn":[0.002080230802],"iteration":925,"passed_time":155.0171234,"remaining_time":12.38797746},
{"learn":[0.002077387816],"iteration":926,"passed_time":155.2071875,"remaining_time":12.22235673},
{"learn":[0.002074193444],"iteration":927,"passed_time":155.3995192,"remaining_time":12.05685925},
{"learn":[0.002064582001],"iteration":928,"passed_time":155.5385207,"remaining_time":11.88722817},
{"learn":[0.002062496855],"iteration":929,"passed_time":155.6775892,"remaining_time":11.71766801},
{"learn":[0.002048527144],"iteration":930,"passed_time":155.8172779,"remaining_time":11.54821931},
{"learn":[0.002046582632],"iteration":931,"passed_time":155.9767054,"remaining_time":11.38027464},
{"learn":[0.002043786986],"iteration":932,"passed_time":156.1532884,"remaining_time":11.21358019},
{"learn":[0.002041566158],"iteration":933,"passed_time":156.3237715,"remaining_time":11.04643353},
{"learn":[0.002039554893],"iteration":934,"passed_time":156.480283,"remaining_time":10.87830844},
{"learn":[0.002037720313],"iteration":935,"passed_time":156.6363675,"remaining_time":10.71017897},
{"learn":[0.002035415896],"iteration":936,"passed_time":156.7956764,"remaining_time":10.54229201},
{"learn":[0.002033702538],"iteration":937,"passed_time":156.9614342,"remaining_time":10.3748496},
{"learn":[0.002031019598],"iteration":938,"passed_time":157.143425,"remaining_time":10.20846531},
{"learn":[0.002028733602],"iteration":939,"passed_time":157.3175423,"remaining_time":10.04154525},
{"learn":[0.002027130176],"iteration":940,"passed_time":157.4589382,"remaining_time":9.872558292},
{"learn":[0.00202483705],"iteration":941,"passed_time":157.6342442,"remaining_time":9.705717795},
{"learn":[0.002022129746],"iteration":942,"passed_time":157.8092193,"remaining_time":9.538839346},
{"learn":[0.002019739166],"iteration":943,"passed_time":157.9742996,"remaining_time":9.371356759},
{"learn":[0.002013494026],"iteration":944,"passed_time":158.1139013,"remaining_time":9.202396373},
{"learn":[0.002012143346],"iteration":945,"passed_time":158.2644769,"remaining_time":9.034124473},
{"learn":[0.002009798125],"iteration":946,"passed_time":158.4377436,"remaining_time":8.867159884},
{"learn":[0.002007246708],"iteration":947,"passed_time":158.5990101,"remaining_time":8.699523758},
{"learn":[0.001999869167],"iteration":948,"passed_time":158.7364393,"remaining_time":8.530620026},
{"learn":[0.001997152158],"iteration":949,"passed_time":158.903857,"remaining_time":8.363360895},
{"learn":[0.001994755041],"iteration":950,"passed_time":159.07117,"remaining_time":8.196096035},
{"learn":[0.001993010387],"iteration":951,"passed_time":159.2287959,"remaining_time":8.028342648},
{"learn":[0.001990235738],"iteration":952,"passed_time":159.4074958,"remaining_time":7.861649844},
{"learn":[0.001988225464],"iteration":953,"passed_time":159.5696446,"remaining_time":7.694133806},
{"learn":[0.001985144589],"iteration":954,"passed_time":159.7131108,"remaining_time":7.525748674},
{"learn":[0.001982549396],"iteration":955,"passed_time":159.9008452,"remaining_time":7.359453125},
{"learn":[0.001979994017],"iteration":956,"passed_time":160.0666987,"remaining_time":7.192129616},
{"learn":[0.001977202927],"iteration":957,"passed_time":160.2403088,"remaining_time":7.025149237},
{"learn":[0.001974186229],"iteration":958,"passed_time":160.3786657,"remaining_time":6.856647856},
{"learn":[0.001971056231],"iteration":959,"passed_time":160.5659979,"remaining_time":6.69024991},
{"learn":[0.001969059625],"iteration":960,"passed_time":160.7351257,"remaining_time":6.523069618},
{"learn":[0.001967431241],"iteration":961,"passed_time":160.8919246,"remaining_time":6.355398267},
{"learn":[0.001965273797],"iteration":962,"passed_time":161.066769,"remaining_time":6.188442839},
{"learn":[0.001963529737],"iteration":963,"passed_time":161.2279537,"remaining_time":6.020960927},
{"learn":[0.001960880074],"iteration":964,"passed_time":161.426192,"remaining_time":5.854835978},
{"learn":[0.001957825543],"iteration":965,"passed_time":161.6276558,"remaining_time":5.688758072},
{"learn":[0.001955362467],"iteration":966,"passed_time":161.8040944,"remaining_time":5.521752962},
{"learn":[0.001952915237],"iteration":967,"passed_time":161.9758594,"remaining_time":5.354573866},
{"learn":[0.001950146728],"iteration":968,"passed_time":162.166387,"remaining_time":5.18798555},
{"learn":[0.001948106743],"iteration":969,"passed_time":162.3537023,"remaining_time":5.021248525},
{"learn":[0.001945276038],"iteration":970,"passed_time":162.55447,"remaining_time":4.854870886},
{"learn":[0.001944034299],"iteration":971,"passed_time":162.7130539,"remaining_time":4.687207313},
{"learn":[0.00194232629],"iteration":972,"passed_time":162.8684496,"remaining_time":4.519473936},
{"learn":[0.001939333162],"iteration":973,"passed_time":163.075466,"remaining_time":4.353143856},
{"learn":[0.001937264654],"iteration":974,"passed_time":163.2478417,"remaining_time":4.185842094},
{"learn":[0.001935032535],"iteration":975,"passed_time":163.4342962,"remaining_time":4.018876135},
{"learn":[0.001932792493],"iteration":976,"passed_time":163.6123923,"remaining_time":3.851673514},
{"learn":[0.001930883238],"iteration":977,"passed_time":163.7775793,"remaining_time":3.684158226},
{"learn":[0.001928480971],"iteration":978,"passed_time":163.9640249,"remaining_time":3.517103701},
{"learn":[0.001926155162],"iteration":979,"passed_time":164.1433151,"remaining_time":3.349863574},
{"learn":[0.001920797997],"iteration":980,"passed_time":164.2812715,"remaining_time":3.181798326},
{"learn":[0.001918272924],"iteration":981,"passed_time":164.4539664,"remaining_time":3.014431157},
{"learn":[0.001915410526],"iteration":982,"passed_time":164.5933092,"remaining_time":2.846476354},
{"learn":[0.001913628634],"iteration":983,"passed_time":164.7501639,"remaining_time":2.678864454},
{"learn":[0.001911201212],"iteration":984,"passed_time":164.9403671,"remaining_time":2.511782241},
{"learn":[0.001909236298],"iteration":985,"passed_time":165.1096044,"remaining_time":2.344355437},
{"learn":[0.001907035871],"iteration":986,"passed_time":165.2845413,"remaining_time":2.177000037},
{"learn":[0.00190472254],"iteration":987,"passed_time":165.4581883,"remaining_time":2.009613623},
{"learn":[0.001902184988],"iteration":988,"passed_time":165.6396284,"remaining_time":1.842301226},
{"learn":[0.001899955246],"iteration":989,"passed_time":165.8250677,"remaining_time":1.675000684},
{"learn":[0.001897802357],"iteration":990,"passed_time":166.005029,"remaining_time":1.507613785},
{"learn":[0.001896579238],"iteration":991,"passed_time":166.1563274,"remaining_time":1.339970382},
{"learn":[0.001894840526],"iteration":992,"passed_time":166.3228981,"remaining_time":1.172467559},
{"learn":[0.001892690014],"iteration":993,"passed_time":166.4889756,"remaining_time":1.004963635},
{"learn":[0.001890557924],"iteration":994,"passed_time":166.6749554,"remaining_time":0.8375625899},
{"learn":[0.00188822538],"iteration":995,"passed_time":166.8521523,"remaining_time":0.6700889652},
{"learn":[0.001885818954],"iteration":996,"passed_time":166.9947953,"remaining_time":0.5024918615},
{"learn":[0.001883538504],"iteration":997,"passed_time":167.1685987,"remaining_time":0.3350072119},
{"learn":[0.001881126532],"iteration":998,"passed_time":167.3614645,"remaining_time":0.1675289935},
{"learn":[0.001879867561],"iteration":999,"passed_time":167.516008,"remaining_time":0}
]}